Workbook

Sheet Instructions & Legend
A1: ISMS-IMP-A.8.10.3 - Third-Party & Cloud Deletion Assessment ISO/IEC 27001:2022 - Control A.8.10: Information Deletion
A3: Document Information
A4: Document ID | B4: ISMS-IMP-A.8.10.3
A5: Workbook Title | B5: Third-Party & Cloud Deletion Assessment
A6: Control Reference | B6: ISO/IEC 27001:2022 - Control A.8.10: Information Deletion
A7: Version | B7: 1.0
A8: Assessment Date
A9: Completed By
A10: Organisation
A12: Instructions
A13: 1. Complete assessment sheets 2–6 in order, filling in all yellow-highlighted cells.
A14: 2. Use dropdown menus where provided for consistency.
A15: 3. Link supporting evidence to the Evidence Register using Column N.
A16: 4. Review the Summary Dashboard for overall compliance status.
A17: 5. Obtain approval using the Approval Sign-Off sheet.
A19: Status Legend
A20: Symbol | B20: Status | C20: Description
A21: ✓ | B21: Compliant / Complete | C21: Requirement fully met
A22: ⚠ | B22: Partial / In Progress | C22: Partially met or in progress
A23: ✗ | B23: Non-Compliant / Not Started | C23: Requirement not met
A24: — | B24: Not Applicable | C24: Not applicable to this assessment

Sheet 2. Cloud Provider Deletion
A1: SHEET 2: CLOUD PROVIDER DELETION
A2: Policy Reference: ISMS-POL-A.8.10-S2.4, Section 2.4.1
A4: ASSESSMENT QUESTION: Do we have documented deletion capabilities, contractual agreements, and performance metrics for all cloud infrastructure and platform providers?
A7: Complete the yellow-highlighted cells below. Use dropdowns where provided. Reference ISMS-REF-A.5.23 for Provider Tier definitions. Link evidence in Column N to Evidence Register sheet.
A9: Provider / Vendor Name | B9: Service Type | C9: Business Owner | D9: Data Categories Processed | E9: Provider Tier | F9: Status | G9: Contract Start Date | H9: Last Contract Review | I9: Next Contract Review | J9: Gap Identified | K9: Remediation Plan | L9: Target Completion | M9: Risk Level | N9: Evidence Reference | O9: Notes / Comments | P9: Remediation Owner | Q9: Budget Required | R9: Deletion Method | S9: Deletion SLA (Days) | T9: Certificate Provided | U9: Multi-Region Verified
A25: COMPLIANCE CHECKLIST - Mark ✅ or {XMARK}
A26: 1. | B26: All cloud providers in use are identified and documented
A27: 2. | B27: Provider tier assigned per ISMS-REF-A.5.23 classification
A28: 3. | B28: Data Processing Agreement (DPA) signed for all providers
A29: 4. | B29: DPA includes specific deletion obligations and timeline
A30: 5. | B30: Deletion method documented (API, console, support ticket)
A31: 6. | B31: API-based deletion implemented for Tier 1-3 providers
A32: 7. | B32: Deletion SLA documented and reasonable (≤30 days preferred)
A33: 8. | B33: Certificate of Deletion available (automatic or on request)
A34: 9. | B34: Multi-region/multi-zone deletion tested and verified
A35: 10. | B35: Snapshot and backup deletion procedures documented
A36: 11. | B36: Account closure deletion behaviour documented
A37: 12. | B37: Provider notifications sent for subprocessor changes
... A40: 15. | B40: Provider included in ISMS-REF-A.5.23 registry (or add if new)
A42: Major Cloud Provider Deletion Capabilities (See ISMS-REF-A.5.23 for complete details)
A43: Provider | B43: Tier | C43: Deletion Method | D43: Certificate Available
A44: AWS | B44: Tier 1 | C44: API Delete, Console | D44: On request
A45: Microsoft Azure | B45: Tier 1 | C45: API Delete, Portal | D45: On request
A46: Google Cloud | B46: Tier 1 | C46: API Delete, Console | D46: On request
A47: Oracle Cloud | B47: Tier 2 | C47: API Delete, Console | D47: On request
A48: IBM Cloud | B48: Tier 2 | C48: API Delete, Console | D48: On request
A49: DigitalOcean | B49: Tier 3 | C49: API Delete, Console | D49: On request
A51: Deletion SLA Best Practices
A52: Data Sensitivity | B52: Recommended SLA | C52: Rationale
A53: Restricted (health, financial) | B53: ≤7 days | C53: High sensitivity, regulatory risk
A54: Confidential | B54: ≤30 days | C54: GDPR default timeframe
A55: Internal | B55: ≤60 days | C55: Business data, moderate sensitivity
A56: Public | B56: ≤90 days | C56: Low sensitivity, operational flexibility
A58: EXCEPTIONS / DEVIATIONS
A59: Document any exceptions or deviations from requirements here:

Sheet 3. SaaS Application Deletion
A1: SHEET 3: SAAS APPLICATION DELETION
A2: Policy Reference: ISMS-POL-A.8.10-S2.4, Section 2.4.2
A4: ASSESSMENT QUESTION: Can we effectively delete data from all SaaS applications, including obtaining confirmation and managing data export if needed?
A7: Complete the yellow-highlighted cells below. Use dropdowns where provided. Reference ISMS-REF-A.5.23 for Provider Tier definitions. Link evidence in Column N to Evidence Register sheet.
A9: Provider / Vendor Name | B9: Service Type | C9: Business Owner | D9: Data Categories Processed | E9: Provider Tier | F9: Status | G9: Contract Start Date | H9: Last Contract Review | I9: Next Contract Review | J9: Gap Identified | K9: Remediation Plan | L9: Target Completion | M9: Risk Level | N9: Evidence Reference | O9: Notes / Comments | P9: Remediation Owner | Q9: Budget Required | R9: Admin Portal Access | S9: Data Export Available | T9: Deletion Request Method | U9: GDPR DPA Signed
A25: COMPLIANCE CHECKLIST - Mark ✅ or {XMARK}
A26: 1. | B26: All SaaS applications in use are identified and documented
A27: 2. | B27: Business owners assigned for each SaaS application
A28: 3. | B28: Data Processing Agreement (DPA) signed for SaaS handling personal data
A29: 4. | B29: DPA includes deletion obligations and timeline
A30: 5. | B30: Admin portal access verified (ability to manage data)
A31: 6. | B31: Data export capability tested (before deletion if needed)
A32: 7. | B32: Deletion request method documented (self-service, ticket, etc.)
A33: 8. | B33: Deletion confirmation process exists
A34: 9. | B34: User account deletion vs. data deletion distinguished
A35: 10. | B35: Shared account deletion procedures documented
A36: 11. | B36: Integration data deletion addressed (APIs, webhooks)
A37: 12. | B37: Backup/archive deletion coordinated
... A40: 15. | B40: GDPR data subject request procedures cover SaaS platforms
A42: Common SaaS Categories and Deletion
A43: Category | B43: Examples | C43: Typical Method | D43: Data Export
A44: CRM | B44: Salesforce, HubSpot | C44: Admin portal delete | D44: API/CSV
A45: HR/Payroll | B45: Workday, BambooHR | C45: Admin + ticket | D45: CSV/API
A46: Marketing | B46: Mailchimp, Braze | C46: Admin delete | D46: API/CSV
A47: Collaboration | B47: Slack, Teams | C47: Admin console | D47: Limited
A48: File Sharing | B48: Dropbox, Box | C48: Admin delete | D48: Download
A49: Analytics | B49: Google Analytics | C49: Admin delete | D49: Limited
A51: SaaS Deletion Challenges
A52: Challenge | B52: Mitigation
A53: User Deletion ≠ Data Deletion | B53: Request data deletion explicitly
A54: Shared Data | B54: Coordinate with data owners
A55: Integration Data | B55: Delete from all integrated systems
A56: Backup Retention | B56: Confirm backup deletion timeline
A57: No Self-Service | B57: Document request process, SLA
A59: EXCEPTIONS / DEVIATIONS
A60: Document any exceptions or deviations from requirements here:

Sheet 4. Vendor Contract Assessment
A1: SHEET 4: VENDOR CONTRACT ASSESSMENT
A2: Policy Reference: ISMS-POL-A.8.10-S2.4, Section 2.4.3
A4: ASSESSMENT QUESTION: Do all vendor contracts include appropriate deletion clauses, SLAs, and audit rights to ensure data deletion compliance?
A7: Complete the yellow-highlighted cells below. Use dropdowns where provided. Reference ISMS-REF-A.5.23 for Provider Tier definitions. Link evidence in Column N to Evidence Register sheet.
A9: Provider / Vendor Name | B9: Service Type | C9: Business Owner | D9: Data Categories Processed | E9: Provider Tier | F9: Status | G9: Contract Start Date | H9: Last Contract Review | I9: Next Contract Review | J9: Gap Identified | K9: Remediation Plan | L9: Target Completion | M9: Risk Level | N9: Evidence Reference | O9: Notes / Comments | P9: Remediation Owner | Q9: Budget Required | R9: Deletion Clause Present | S9: Deletion Timeline Specified | T9: Certificate of Deletion | U9: Audit Rights
A25: COMPLIANCE CHECKLIST - Mark ✅ or {XMARK}
A26: 1. | B26: All vendor contracts reviewed for deletion clauses
A27: 2. | B27: Deletion clause specificity assessed (specific vs. generic)
A28: 3. | B28: Deletion timeline explicitly stated (not just 'reasonable time')
A29: 4. | B29: Certificate of Deletion either required or available on request
A30: 5. | B30: Audit rights include ability to verify deletion compliance
A31: 6. | B31: Subprocessor usage disclosed and governed
A32: 7. | B32: Data return option available as alternative to deletion
A33: 8. | B33: Contract renewal triggers deletion clause review
A34: 9. | B34: New vendor onboarding includes deletion clause requirement
A35: 10. | B35: Vendor contract template updated with deletion requirements
A36: 11. | B36: Legal/Procurement engaged for contract negotiations
A37: 12. | B37: High-risk vendors (Tier 1-3, Restricted data) have strongest clauses
... A40: 15. | B40: Contracts reviewed at least every 3 years
A42: Deletion Clause Strength
A43: Type | B43: Strength | C43: Recommended For
A44: Specific with timeline and certificate | B44: Excellent | C44: Tier 1-3, Restricted data
A45: Generic with timeline (≤90 days) | B45: Acceptable | C45: Tier 4-6, Confidential
A46: Generic only | B46: Insufficient | C46: Not recommended
A47: Absent | B47: Non-Compliant | C47: Requires amendment
A49: Certificate of Deletion Elements
A50: Element | B50: Example
A51: Date of Deletion | B51: Deleted on: 2025-12-15
A52: Scope | B52: All customer records for Company X
A53: Method | B53: Secure deletion per NIST SP 800-88 Rev. 2
A54: Systems | B54: Production DB, backups, archives
A55: Verification | B55: Forensic verification completed
A56: Authorised Signatory | B56: Signed by: DPO
A58: EXCEPTIONS / DEVIATIONS
A59: Document any exceptions or deviations from requirements here:

Sheet 5. Subprocessor Mapping
A1: SHEET 5: SUBPROCESSOR MAPPING
A2: Policy Reference: ISMS-POL-A.8.10-S2.4, Section 2.4.4
A4: ASSESSMENT QUESTION: Do we know all subprocessors in our vendor supply chain, and can we coordinate deletion across the entire chain?
A7: Complete the yellow-highlighted cells below. Use dropdowns where provided. Reference ISMS-REF-A.5.23 for Provider Tier definitions. Link evidence in Column N to Evidence Register sheet.
A9: Provider / Vendor Name | B9: Service Type | C9: Business Owner | D9: Data Categories Processed | E9: Provider Tier | F9: Status | G9: Contract Start Date | H9: Last Contract Review | I9: Next Contract Review | J9: Gap Identified | K9: Remediation Plan | L9: Target Completion | M9: Risk Level | N9: Evidence Reference | O9: Notes / Comments | P9: Remediation Owner | Q9: Budget Required | R9: Subprocessor Count | S9: Subprocessor List Current | T9: Deletion Flow Documented | U9: Subprocessor Deletion SLA
A25: COMPLIANCE CHECKLIST - Mark ✅ or {XMARK}
A26: 1. | B26: All primary vendors (processors) identified
A27: 2. | B27: Subprocessor disclosure obtained from each vendor
A28: 3. | B28: Subprocessor count documented and current
A29: 4. | B29: Subprocessor list reviewed at least annually
A30: 5. | B30: Vendor contractually obligated to notify of subprocessor changes
A31: 6. | B31: Data flow diagram created for critical data categories
A32: 7. | B32: Deletion flow documented (prime vendor → subprocessor deletion)
A33: 8. | B33: Subprocessor deletion SLA understood (covered by prime or separate)
A34: 9. | B34: Subprocessor DPAs flow down from prime vendor
A35: 10. | B35: High-risk subprocessors identified (non-EU, Tier 9/10)
A36: 11. | B36: Subprocessor changes trigger risk assessment
A37: 12. | B37: Deletion requests explicitly include subprocessor deletion
... A40: 15. | B40: Shadow subprocessors investigated (undisclosed usage)
A42: Common Subprocessor Categories
A43: Primary Vendor | B43: Common Subprocessors | C43: Coordination
A44: Cloud Provider | B44: CDN, Monitoring, Logging | C44: Via prime APIs
A45: SaaS CRM | B45: Email, Analytics, Payment | C45: Prime coordinates
A46: HR/Payroll | B46: Background check, Benefits | C46: Often manual
A47: Marketing | B47: Email, SMS, Ad networks | C47: API/dashboard
A48: File Sharing | B48: Preview, Virus scan, OCR | C48: Automatic via prime
A50: GDPR Article 28(2) Requirements
A51: Requirement | B51: Verification
A52: Prior Authorisation | B52: Authorised in contract?
A53: Notification of Changes | B53: Notification process?
A54: Objection Rights | B54: Objection clause present?
A55: Same Obligations | B55: Flow-down confirmed?
A56: Prime Liability | B56: Liability clause present?
A58: EXCEPTIONS / DEVIATIONS
A59: Document any exceptions or deviations from requirements here:

Sheet 6. Shadow IT Assessment
A1: SHEET 6: SHADOW IT ASSESSMENT
A2: Policy Reference: ISMS-POL-A.8.10-S2.4, Section 2.4.5
A4: ASSESSMENT QUESTION: Are vendors meeting their deletion SLAs, providing certificates when required, and is performance monitored over time?
A7: Complete the yellow-highlighted cells below. Use dropdowns where provided. Reference ISMS-REF-A.5.23 for Provider Tier definitions. Link evidence in Column N to Evidence Register sheet.
A9: Provider / Vendor Name | B9: Service Type | C9: Business Owner | D9: Data Categories Processed | E9: Provider Tier | F9: Status | G9: Contract Start Date | H9: Last Contract Review | I9: Next Contract Review | J9: Gap Identified | K9: Remediation Plan | L9: Target Completion | M9: Risk Level | N9: Evidence Reference | O9: Notes / Comments | P9: Remediation Owner | Q9: Budget Required | R9: Deletion Requests (Last 12M) | S9: Average Response Time (Days) | T9: Certificates Received | U9: Incidents / Failures
A25: COMPLIANCE CHECKLIST - Mark ✅ or {XMARK}
A26: 1. | B26: Deletion request log maintained for all vendors
A27: 2. | B27: Response time tracked per vendor
A28: 3. | B28: SLA compliance calculated (actual vs. contracted)
A29: 4. | B29: Certificate of Deletion requested for high-value deletions
A30: 5. | B30: Certificate completeness reviewed
A31: 6. | B31: Deletion incidents documented and investigated
A32: 7. | B32: Root cause analysis performed for failed deletions
A33: 8. | B33: Vendor escalation procedures exist for SLA breaches
A34: 9. | B34: Quarterly vendor performance review conducted
A35: 10. | B35: Underperforming vendors identified and remediated
A36: 11. | B36: Performance metrics reported to management
A37: 12. | B37: Vendor scorecard includes deletion performance
... A40: 15. | B40: Performance data feeds into vendor risk assessment
A42: Performance Metrics
A43: Metric | B43: Target | C43: Use Case
A44: Average Response Time | B44: ≤ Contracted SLA | C44: Overall performance
A45: SLA Compliance Rate | B45: ≥ 95% | C45: Contract compliance
A46: Certificate Completion | B46: 100% (critical vendors) | C46: Documentation quality
A47: Incident Rate | B47: < 5% | C47: Reliability
A49: Deletion Incident Types
A50: Type | B50: Severity | C50: Remediation
A51: SLA Breach | B51: Medium-High | C51: Escalate, track pattern
A52: Incomplete Deletion | B52: High | C52: Re-request, verify
A53: No Certificate | B53: Medium | C53: Request, document
A54: Subprocessor Failure | B54: Critical | C54: Escalate to prime, audit
A55: Vendor Refusal | B55: Critical | C55: Legal escalation, exit
A57: EXCEPTIONS / DEVIATIONS
A58: Document any exceptions or deviations from requirements here:

Sheet Evidence Register
A1: EVIDENCE REGISTER
A2: List all evidence files/documents referenced in this assessment (audit traceability).
A4: Evidence ID | B4: Category | C4: Description | D4: Source Document | E4: Date Collected | F4: Collected By | G4: Status | H4: Notes
A5: EV-001
A6: EV-002
A7: EV-003
A8: EV-004
A9: EV-005
A10: EV-006
A11: EV-007
A12: EV-008
A13: EV-009
A14: EV-010
A15: EV-011
A16: EV-012
... A104: EV-100

Sheet Summary Dashboard
A1: Third-Party & Cloud Deletion Assessment — SUMMARY DASHBOARD
A2: Summary Dashboard | Third-Party & Cloud Deletion Assessment | Generated: 20260307
A4: TABLE 1 – COMPLIANCE ASSESSMENT SUMMARY
A5: Assessment Area | B5: Total Items | C5: Compliant | D5: Partial | E5: Non-Compliant | F5: N/A | G5: Compliance %
A6: Cloud Provider Deletion | B6: =C6+D6+E6+F6 | C6: =COUNTIF('2. Cloud Provider Deletion'!F10:F100,"✅ Compliant") | D6: =COUNTIF('2. Cloud Provider Deletion'!F10:F100,"⚠️ Partial") | E6: =COUNTIF('2. Cloud Provider Deletion'!F10:F100,"❌ Non-Compliant") | F6: =COUNTIF('2. Cloud Provider Deletion'!F10:F100,"N/A") | G6: =IF((B6-F6)=0,0,C6/(B6-F6))
A7: SaaS Application Deletion | B7: =C7+D7+E7+F7 | C7: =COUNTIF('3. SaaS Application Deletion'!F10:F100,"✅ Compliant") | D7: =COUNTIF('3. SaaS Application Deletion'!F10:F100,"⚠️ Partial") | E7: =COUNTIF('3. SaaS Application Deletion'!F10:F100,"❌ Non-Compliant") | F7: =COUNTIF('3. SaaS Application Deletion'!F10:F100,"N/A") | G7: =IF((B7-F7)=0,0,C7/(B7-F7))
A8: Vendor Contract Assessment | B8: =C8+D8+E8+F8 | C8: =COUNTIF('4. Vendor Contract Assessment'!F10:F100,"✅ Compliant") | D8: =COUNTIF('4. Vendor Contract Assessment'!F10:F100,"⚠️ Partial") | E8: =COUNTIF('4. Vendor Contract Assessment'!F10:F100,"❌ Non-Compliant") | F8: =COUNTIF('4. Vendor Contract Assessment'!F10:F100,"N/A") | G8: =IF((B8-F8)=0,0,C8/(B8-F8))
A9: Subprocessor Mapping | B9: =C9+D9+E9+F9 | C9: =COUNTIF('5. Subprocessor Mapping'!F10:F100,"✅ Compliant") | D9: =COUNTIF('5. Subprocessor Mapping'!F10:F100,"⚠️ Partial") | E9: =COUNTIF('5. Subprocessor Mapping'!F10:F100,"❌ Non-Compliant") | F9: =COUNTIF('5. Subprocessor Mapping'!F10:F100,"N/A") | G9: =IF((B9-F9)=0,0,C9/(B9-F9))
A10: Shadow IT Assessment | B10: =C10+D10+E10+F10 | C10: =COUNTIF('6. Shadow IT Assessment'!F10:F100,"✅ Compliant") | D10: =COUNTIF('6. Shadow IT Assessment'!F10:F100,"⚠️ Partial") | E10: =COUNTIF('6. Shadow IT Assessment'!F10:F100,"❌ Non-Compliant") | F10: =COUNTIF('6. Shadow IT Assessment'!F10:F100,"N/A") | G10: =IF((B10-F10)=0,0,C10/(B10-F10))
A11: TOTAL | B11: =SUM(B6:B10) | C11: =SUM(C6:C10) | D11: =SUM(D6:D10) | E11: =SUM(E6:E10) | F11: =SUM(F6:F10) | G11: =IF((B11-F11)=0,0,C11/(B11-F11))
A13: TABLE 2 – KEY METRICS
A14: Metric | B14: Value | C14: Target
A15: Overall Compliance Rate | B15: =IFERROR(G11,"N/A") | C15: ≥ 80%
A16: Cloud Providers with DPA Including Deletion Clause | B16: =IFERROR(COUNTIF('4. Vendor Contract Assessment'!F10:F100,"✅ Compliant"),0) | C16: 100%
A17: SaaS Applications with Deletion Procedures Documented | B17: =IFERROR(COUNTIF('3. SaaS Application Deletion'!F10:F100,"✅ Compliant"),0) | C17: 100%
A18: Subprocessors with Deletion Flows Verified | B18: =IFERROR(COUNTIF('5. Subprocessor Mapping'!F10:F100,"✅ Compliant"),0) | C18: 100%
A19: Shadow IT Services Identified and Remediated | B19: =IFERROR(COUNTIF('6. Shadow IT Assessment'!F10:F100,"✅ Compliant"),0) | C19: 100%
A20: Non-Compliant Vendor Items Requiring Remediation | B20: =IFERROR(SUM(E6:E10),0) | C20: 0
A22: TABLE 3 – KEY FINDINGS & RECOMMENDATIONS
A23: # | B23: Finding | C23: Impact | D23: Recommendation | E23: Priority | F23: Status | G23: Notes
A24: 1 | B24: Data Processing Agreements may lack specific deletion clauses or timelines | C24: High | D24: Audit all DPAs and add deletion obligations per GDPR Art. 28(3)(g) | E24: P1 | F24: Open | G24: GDPR Art. 28
A25: 2 | B25: Shadow IT services may process data without deletion controls | C25: High | D25: Conduct shadow IT discovery and enforce approved vendor list | E25: P1 | F25: Open
A26: 3 | B26: Subprocessor deletion chain-of-custody may not be verified | C26: Medium | D26: Map all subprocessors and obtain deletion confirmation for each | E26: P2 | F26: Open
A27: 4 | B27: SaaS application deletion procedures may rely on account closure only | C27: Medium | D27: Request and validate deletion certificates from all SaaS providers | E27: P2 | F27: Open

Sheet Approval Sign-Off
A1: ASSESSMENT APPROVAL AND SIGN-OFF
A3: ASSESSMENT SUMMARY
A4: Document: | B4: ISMS-IMP-A.8.10.3 - Third-Party & Cloud Deletion Assessment
A5: Assessment Period:
A6: Overall Compliance: | B6: =IFERROR(AVERAGE('Summary Dashboard'!G6:G10),"")
A7: Assessment Status:
A10: COMPLETED BY (IT SECURITY)
A11: Name:
A12: Title:
A13: Date:
A14: Signature:
A15: Comments:
A17: REVIEWED BY (ISO)
A18: Name:
A19: Title:
A20: Date:
A21: Signature:
... A37: Special Considerations:
