Workbook

Sheet Instructions & Legend
A1: ISMS-IMP-A.8.6-Assessment-2 - Capacity Forecasting & Planning ISO/IEC 27001:2022 - Control A.8.6: Capacity Management
A3: Document Information
A4: Document ID | B4: ISMS-IMP-A.8.6-Assessment-2
A5: Workbook Title | B5: Capacity Forecasting & Planning
A6: Control Reference | B6: ISO/IEC 27001:2022 - Control A.8.6: Capacity Management
A7: Version | B7: 1.0
A8: Assessment Date
A9: Completed By
A10: Organisation
A12: Instructions
A13: 1. Complete each worksheet tab for applicable systems/services.
A14: 2. Use dropdown menus for standardised entries (Status, Remediation, etc.).
A15: 3. Fill in yellow-highlighted cells with your information.
A16: 4. If Status = Partial or Non-Compliant, complete the Exception/Deviation section.
A17: 5. Check all applicable items in the Compliance Checklist for each section.
A18: 6. Provide evidence location/path for each implementation entry.
A19: 7. Summary Dashboard auto-calculates compliance statistics.
A20: 8. Maintain the Evidence Register for audit traceability.
... A23: Status Legend
A24: Symbol | B24: Status | C24: Description
A25: ✓ | B25: Compliant / Complete | C25: Requirement fully met
A26: ⚠ | B26: Partial / In Progress | C26: Partially met or in progress
A27: ✗ | B27: Non-Compliant / Not Started | C27: Requirement not met
A28: — | B28: Not Applicable | C28: Not applicable to this assessment

Sheet Historical Utilization
A1: HISTORICAL CAPACITY UTILIZATION DATA
A2: Import historical utilization data from monitoring tools for trend analysis (6-24 months recommended)
A3: Month/Date | B3: Resource Name | C3: Utilization (%) | D3: Peak Utilization (%) | E3: Notes | F3: Data Source
A4: 01.01.2026 | B4: server01.example.com | C4: 65.4 | D4: 78.2 | E4: Q1 historical data | F4: Prometheus

Sheet Trend Analysis
A1: CAPACITY TREND ANALYSIS
A2: Growth rates, seasonal patterns, and regression analysis per resource
A3: Resource Name | B3: Trend Method | C3: Growth Rate (% per month) | D3: R-Squared | E3: Seasonal Pattern | F3: Notes | G3: Analyst
A4: server01.example.com | B4: Linear Regression | C4: 2.3 | D4: 0.87 | E4: None | F4: Steady monthly growth pattern | G4: IT Operations

Sheet Capacity Forecasts
A1: CAPACITY FORECASTS (6, 12, AND 24 MONTHS)
A2: Short-, medium-, and long-term capacity projections per resource (columns D-F auto-calculate)
A3: Resource Name | B3: Current Utilization (%) | C3: Growth Rate (%/month) | D3: 6-Month Forecast (%) | E3: 12-Month Forecast (%) | F3: 24-Month Forecast (%) | G3: Confidence | H3: Assumptions | I3: Forecast Date
A4: server01.example.com | B4: 65.4 | C4: 2.3 | D4: =IF(AND(B4<>"",C4<>""),B4+(C4*6),"") | E4: =IF(AND(B4<>"",C4<>""),B4+(C4*12),"") | F4: =IF(AND(B4<>"",C4<>""),B4+(C4*24),"") | G4: High | H4: Based on 12-month historical trend | I4: 22.02.2026
D5: =IF(AND(B5<>"",C5<>""),B5+(C5*6),"") | E5: =IF(AND(B5<>"",C5<>""),B5+(C5*12),"") | F5: =IF(AND(B5<>"",C5<>""),B5+(C5*24),"")
D6: =IF(AND(B6<>"",C6<>""),B6+(C6*6),"") | E6: =IF(AND(B6<>"",C6<>""),B6+(C6*12),"") | F6: =IF(AND(B6<>"",C6<>""),B6+(C6*24),"")
D7: =IF(AND(B7<>"",C7<>""),B7+(C7*6),"") | E7: =IF(AND(B7<>"",C7<>""),B7+(C7*12),"") | F7: =IF(AND(B7<>"",C7<>""),B7+(C7*24),"")
D8: =IF(AND(B8<>"",C8<>""),B8+(C8*6),"") | E8: =IF(AND(B8<>"",C8<>""),B8+(C8*12),"") | F8: =IF(AND(B8<>"",C8<>""),B8+(C8*24),"")
D9: =IF(AND(B9<>"",C9<>""),B9+(C9*6),"") | E9: =IF(AND(B9<>"",C9<>""),B9+(C9*12),"") | F9: =IF(AND(B9<>"",C9<>""),B9+(C9*24),"")
D10: =IF(AND(B10<>"",C10<>""),B10+(C10*6),"") | E10: =IF(AND(B10<>"",C10<>""),B10+(C10*12),"") | F10: =IF(AND(B10<>"",C10<>""),B10+(C10*24),"")
D11: =IF(AND(B11<>"",C11<>""),B11+(C11*6),"") | E11: =IF(AND(B11<>"",C11<>""),B11+(C11*12),"") | F11: =IF(AND(B11<>"",C11<>""),B11+(C11*24),"")
D12: =IF(AND(B12<>"",C12<>""),B12+(C12*6),"") | E12: =IF(AND(B12<>"",C12<>""),B12+(C12*12),"") | F12: =IF(AND(B12<>"",C12<>""),B12+(C12*24),"")
D13: =IF(AND(B13<>"",C13<>""),B13+(C13*6),"") | E13: =IF(AND(B13<>"",C13<>""),B13+(C13*12),"") | F13: =IF(AND(B13<>"",C13<>""),B13+(C13*24),"")
D14: =IF(AND(B14<>"",C14<>""),B14+(C14*6),"") | E14: =IF(AND(B14<>"",C14<>""),B14+(C14*12),"") | F14: =IF(AND(B14<>"",C14<>""),B14+(C14*24),"")
D15: =IF(AND(B15<>"",C15<>""),B15+(C15*6),"") | E15: =IF(AND(B15<>"",C15<>""),B15+(C15*12),"") | F15: =IF(AND(B15<>"",C15<>""),B15+(C15*24),"")
D16: =IF(AND(B16<>"",C16<>""),B16+(C16*6),"") | E16: =IF(AND(B16<>"",C16<>""),B16+(C16*12),"") | F16: =IF(AND(B16<>"",C16<>""),B16+(C16*24),"")
... D54: =IF(AND(B54<>"",C54<>""),B54+(C54*6),"") | E54: =IF(AND(B54<>"",C54<>""),B54+(C54*12),"") | F54: =IF(AND(B54<>"",C54<>""),B54+(C54*24),"")

Sheet Capacity Exhaustion
A1: CAPACITY EXHAUSTION PROJECTIONS
A2: Forecasted dates when resources will reach capacity thresholds (columns E-G auto-calculate)
A3: Resource Name | B3: Current (%) | C3: Threshold (%) | D3: Growth Rate (%/mo) | E3: Months to Threshold | F3: Exhaustion Date | G3: Urgency | H3: Action Required
A4: server01.example.com | B4: 65.4 | C4: 85 | D4: 2.3 | E4: =IF(AND(B4<>"",C4<>"",D4<>"",D4>0),(C4-B4)/D4,"") | F4: =IF(E4<>"",TODAY()+(E4*30),"") | G4: =IF(A4="","",IF(E4="","No Risk",IF(E4<=0,"CRITICAL",IF(E4<=3,"Immediate (0-3mo)",IF(E4<=6,"Short-term (3-6mo)",IF(E4<=12,"Medium-term (6-12mo)","Long-term (>12mo)")))))) | H4: Initiate capacity expansion planning
E5: =IF(AND(B5<>"",C5<>"",D5<>"",D5>0),(C5-B5)/D5,"") | F5: =IF(E5<>"",TODAY()+(E5*30),"") | G5: =IF(A5="","",IF(E5="","No Risk",IF(E5<=0,"CRITICAL",IF(E5<=3,"Immediate (0-3mo)",IF(E5<=6,"Short-term (3-6mo)",IF(E5<=12,"Medium-term (6-12mo)","Long-term (>12mo)"))))))
E6: =IF(AND(B6<>"",C6<>"",D6<>"",D6>0),(C6-B6)/D6,"") | F6: =IF(E6<>"",TODAY()+(E6*30),"") | G6: =IF(A6="","",IF(E6="","No Risk",IF(E6<=0,"CRITICAL",IF(E6<=3,"Immediate (0-3mo)",IF(E6<=6,"Short-term (3-6mo)",IF(E6<=12,"Medium-term (6-12mo)","Long-term (>12mo)"))))))
E7: =IF(AND(B7<>"",C7<>"",D7<>"",D7>0),(C7-B7)/D7,"") | F7: =IF(E7<>"",TODAY()+(E7*30),"") | G7: =IF(A7="","",IF(E7="","No Risk",IF(E7<=0,"CRITICAL",IF(E7<=3,"Immediate (0-3mo)",IF(E7<=6,"Short-term (3-6mo)",IF(E7<=12,"Medium-term (6-12mo)","Long-term (>12mo)"))))))
E8: =IF(AND(B8<>"",C8<>"",D8<>"",D8>0),(C8-B8)/D8,"") | F8: =IF(E8<>"",TODAY()+(E8*30),"") | G8: =IF(A8="","",IF(E8="","No Risk",IF(E8<=0,"CRITICAL",IF(E8<=3,"Immediate (0-3mo)",IF(E8<=6,"Short-term (3-6mo)",IF(E8<=12,"Medium-term (6-12mo)","Long-term (>12mo)"))))))
E9: =IF(AND(B9<>"",C9<>"",D9<>"",D9>0),(C9-B9)/D9,"") | F9: =IF(E9<>"",TODAY()+(E9*30),"") | G9: =IF(A9="","",IF(E9="","No Risk",IF(E9<=0,"CRITICAL",IF(E9<=3,"Immediate (0-3mo)",IF(E9<=6,"Short-term (3-6mo)",IF(E9<=12,"Medium-term (6-12mo)","Long-term (>12mo)"))))))
E10: =IF(AND(B10<>"",C10<>"",D10<>"",D10>0),(C10-B10)/D10,"") | F10: =IF(E10<>"",TODAY()+(E10*30),"") | G10: =IF(A10="","",IF(E10="","No Risk",IF(E10<=0,"CRITICAL",IF(E10<=3,"Immediate (0-3mo)",IF(E10<=6,"Short-term (3-6mo)",IF(E10<=12,"Medium-term (6-12mo)","Long-term (>12mo)"))))))
E11: =IF(AND(B11<>"",C11<>"",D11<>"",D11>0),(C11-B11)/D11,"") | F11: =IF(E11<>"",TODAY()+(E11*30),"") | G11: =IF(A11="","",IF(E11="","No Risk",IF(E11<=0,"CRITICAL",IF(E11<=3,"Immediate (0-3mo)",IF(E11<=6,"Short-term (3-6mo)",IF(E11<=12,"Medium-term (6-12mo)","Long-term (>12mo)"))))))
E12: =IF(AND(B12<>"",C12<>"",D12<>"",D12>0),(C12-B12)/D12,"") | F12: =IF(E12<>"",TODAY()+(E12*30),"") | G12: =IF(A12="","",IF(E12="","No Risk",IF(E12<=0,"CRITICAL",IF(E12<=3,"Immediate (0-3mo)",IF(E12<=6,"Short-term (3-6mo)",IF(E12<=12,"Medium-term (6-12mo)","Long-term (>12mo)"))))))
E13: =IF(AND(B13<>"",C13<>"",D13<>"",D13>0),(C13-B13)/D13,"") | F13: =IF(E13<>"",TODAY()+(E13*30),"") | G13: =IF(A13="","",IF(E13="","No Risk",IF(E13<=0,"CRITICAL",IF(E13<=3,"Immediate (0-3mo)",IF(E13<=6,"Short-term (3-6mo)",IF(E13<=12,"Medium-term (6-12mo)","Long-term (>12mo)"))))))
E14: =IF(AND(B14<>"",C14<>"",D14<>"",D14>0),(C14-B14)/D14,"") | F14: =IF(E14<>"",TODAY()+(E14*30),"") | G14: =IF(A14="","",IF(E14="","No Risk",IF(E14<=0,"CRITICAL",IF(E14<=3,"Immediate (0-3mo)",IF(E14<=6,"Short-term (3-6mo)",IF(E14<=12,"Medium-term (6-12mo)","Long-term (>12mo)"))))))
E15: =IF(AND(B15<>"",C15<>"",D15<>"",D15>0),(C15-B15)/D15,"") | F15: =IF(E15<>"",TODAY()+(E15*30),"") | G15: =IF(A15="","",IF(E15="","No Risk",IF(E15<=0,"CRITICAL",IF(E15<=3,"Immediate (0-3mo)",IF(E15<=6,"Short-term (3-6mo)",IF(E15<=12,"Medium-term (6-12mo)","Long-term (>12mo)"))))))
E16: =IF(AND(B16<>"",C16<>"",D16<>"",D16>0),(C16-B16)/D16,"") | F16: =IF(E16<>"",TODAY()+(E16*30),"") | G16: =IF(A16="","",IF(E16="","No Risk",IF(E16<=0,"CRITICAL",IF(E16<=3,"Immediate (0-3mo)",IF(E16<=6,"Short-term (3-6mo)",IF(E16<=12,"Medium-term (6-12mo)","Long-term (>12mo)"))))))
... E54: =IF(AND(B54<>"",C54<>"",D54<>"",D54>0),(C54-B54)/D54,"") | F54: =IF(E54<>"",TODAY()+(E54*30),"") | G54: =IF(A54="","",IF(E54="","No Risk",IF(E54<=0,"CRITICAL",IF(E54<=3,"Immediate (0-3mo)",IF(E54<=6,"Short-term (3-6mo)",IF(E54<=12,"Medium-term (6-12mo)","Long-term (>12mo)"))))))

Sheet Planned Expansions
A1: PLANNED CAPACITY EXPANSIONS
A2: Planned capacity additions with timelines, cost estimates, and approval status
A3: Resource Name | B3: Current Capacity | C3: Expansion Amount | D3: New Total Capacity | E3: Planned Date | F3: Lead Time (days) | G3: Status | H3: Cost Estimate | I3: Approval Status | J3: Owner
A4: server01.example.com | B4: 2 TB | C4: 2 TB | D4: 4 TB | E4: 30.06.2026 | F4: 90 | G4: In Procurement | H4: 15,000 | I4: Approved | J4: IT Infrastructure

Sheet Forecast Accuracy
A1: FORECAST ACCURACY VALIDATION
A2: Validation of previous forecasts vs. actual utilization (columns E-G auto-calculate)
A3: Resource Name | B3: Forecast Date | C3: Forecasted Value | D3: Actual Value | E3: Absolute Error | F3: Percentage Error (%) | G3: Accuracy Rating | H3: Lessons Learned
A4: server01.example.com | B4: 01.09.2025 | C4: 75 | D4: 72 | E4: =IF(AND(C4<>"",D4<>""),ABS(C4-D4),"") | F4: =IF(AND(C4<>"",D4<>"",D4<>0),ABS((C4-D4)/D4)*100,"") | G4: =IF(F4="","",IF(F4<=5,"Excellent",IF(F4<=10,"Good",IF(F4<=15,"Acceptable","Poor")))) | H4: Slight underestimate — adjust growth rate model
E5: =IF(AND(C5<>"",D5<>""),ABS(C5-D5),"") | F5: =IF(AND(C5<>"",D5<>"",D5<>0),ABS((C5-D5)/D5)*100,"") | G5: =IF(F5="","",IF(F5<=5,"Excellent",IF(F5<=10,"Good",IF(F5<=15,"Acceptable","Poor"))))
E6: =IF(AND(C6<>"",D6<>""),ABS(C6-D6),"") | F6: =IF(AND(C6<>"",D6<>"",D6<>0),ABS((C6-D6)/D6)*100,"") | G6: =IF(F6="","",IF(F6<=5,"Excellent",IF(F6<=10,"Good",IF(F6<=15,"Acceptable","Poor"))))
E7: =IF(AND(C7<>"",D7<>""),ABS(C7-D7),"") | F7: =IF(AND(C7<>"",D7<>"",D7<>0),ABS((C7-D7)/D7)*100,"") | G7: =IF(F7="","",IF(F7<=5,"Excellent",IF(F7<=10,"Good",IF(F7<=15,"Acceptable","Poor"))))
E8: =IF(AND(C8<>"",D8<>""),ABS(C8-D8),"") | F8: =IF(AND(C8<>"",D8<>"",D8<>0),ABS((C8-D8)/D8)*100,"") | G8: =IF(F8="","",IF(F8<=5,"Excellent",IF(F8<=10,"Good",IF(F8<=15,"Acceptable","Poor"))))
E9: =IF(AND(C9<>"",D9<>""),ABS(C9-D9),"") | F9: =IF(AND(C9<>"",D9<>"",D9<>0),ABS((C9-D9)/D9)*100,"") | G9: =IF(F9="","",IF(F9<=5,"Excellent",IF(F9<=10,"Good",IF(F9<=15,"Acceptable","Poor"))))
E10: =IF(AND(C10<>"",D10<>""),ABS(C10-D10),"") | F10: =IF(AND(C10<>"",D10<>"",D10<>0),ABS((C10-D10)/D10)*100,"") | G10: =IF(F10="","",IF(F10<=5,"Excellent",IF(F10<=10,"Good",IF(F10<=15,"Acceptable","Poor"))))
E11: =IF(AND(C11<>"",D11<>""),ABS(C11-D11),"") | F11: =IF(AND(C11<>"",D11<>"",D11<>0),ABS((C11-D11)/D11)*100,"") | G11: =IF(F11="","",IF(F11<=5,"Excellent",IF(F11<=10,"Good",IF(F11<=15,"Acceptable","Poor"))))
E12: =IF(AND(C12<>"",D12<>""),ABS(C12-D12),"") | F12: =IF(AND(C12<>"",D12<>"",D12<>0),ABS((C12-D12)/D12)*100,"") | G12: =IF(F12="","",IF(F12<=5,"Excellent",IF(F12<=10,"Good",IF(F12<=15,"Acceptable","Poor"))))
E13: =IF(AND(C13<>"",D13<>""),ABS(C13-D13),"") | F13: =IF(AND(C13<>"",D13<>"",D13<>0),ABS((C13-D13)/D13)*100,"") | G13: =IF(F13="","",IF(F13<=5,"Excellent",IF(F13<=10,"Good",IF(F13<=15,"Acceptable","Poor"))))
E14: =IF(AND(C14<>"",D14<>""),ABS(C14-D14),"") | F14: =IF(AND(C14<>"",D14<>"",D14<>0),ABS((C14-D14)/D14)*100,"") | G14: =IF(F14="","",IF(F14<=5,"Excellent",IF(F14<=10,"Good",IF(F14<=15,"Acceptable","Poor"))))
E15: =IF(AND(C15<>"",D15<>""),ABS(C15-D15),"") | F15: =IF(AND(C15<>"",D15<>"",D15<>0),ABS((C15-D15)/D15)*100,"") | G15: =IF(F15="","",IF(F15<=5,"Excellent",IF(F15<=10,"Good",IF(F15<=15,"Acceptable","Poor"))))
E16: =IF(AND(C16<>"",D16<>""),ABS(C16-D16),"") | F16: =IF(AND(C16<>"",D16<>"",D16<>0),ABS((C16-D16)/D16)*100,"") | G16: =IF(F16="","",IF(F16<=5,"Excellent",IF(F16<=10,"Good",IF(F16<=15,"Acceptable","Poor"))))
... E54: =IF(AND(C54<>"",D54<>""),ABS(C54-D54),"") | F54: =IF(AND(C54<>"",D54<>"",D54<>0),ABS((C54-D54)/D54)*100,"") | G54: =IF(F54="","",IF(F54<=5,"Excellent",IF(F54<=10,"Good",IF(F54<=15,"Acceptable","Poor"))))

Sheet Budget Planning
A1: CAPACITY BUDGET PLANNING
A2: Capital and operational expenditure planning for capacity expansions (column E auto-calculates 3-year TCO)
A3: Resource/Project | B3: Quarter | C3: CapEx (CHF) | D3: OpEx (CHF/month) | E3: 3-Year TCO (CHF) | F3: Approval Status | G3: Notes
A4: Storage Expansion - server01 | B4: Q2 | C4: 15000 | D4: 500 | E4: =IF(AND(C4<>"",D4<>""),C4+(D4*12*3),"") | F4: Approved | G4: NAS upgrade for production storage
E5: =IF(AND(C5<>"",D5<>""),C5+(D5*12*3),"")
E6: =IF(AND(C6<>"",D6<>""),C6+(D6*12*3),"")
E7: =IF(AND(C7<>"",D7<>""),C7+(D7*12*3),"")
E8: =IF(AND(C8<>"",D8<>""),C8+(D8*12*3),"")
E9: =IF(AND(C9<>"",D9<>""),C9+(D9*12*3),"")
E10: =IF(AND(C10<>"",D10<>""),C10+(D10*12*3),"")
E11: =IF(AND(C11<>"",D11<>""),C11+(D11*12*3),"")
E12: =IF(AND(C12<>"",D12<>""),C12+(D12*12*3),"")
E13: =IF(AND(C13<>"",D13<>""),C13+(D13*12*3),"")
E14: =IF(AND(C14<>"",D14<>""),C14+(D14*12*3),"")
E15: =IF(AND(C15<>"",D15<>""),C15+(D15*12*3),"")
E16: =IF(AND(C16<>"",D16<>""),C16+(D16*12*3),"")
... E54: =IF(AND(C54<>"",D54<>""),C54+(D54*12*3),"")

Sheet Evidence Register
A1: EVIDENCE REGISTER
A2: List all evidence files/documents referenced in this assessment (audit traceability).
A4: Evidence ID | B4: Assessment Area | C4: Evidence Type | D4: Description | E4: Location/Path | F4: Date Collected | G4: Collected By | H4: Verification Status
A5: EV-001 | B5: Capacity Forecasting | C5: Capacity report | D5: 12-month capacity forecast model with growth projections | E5: /capacity/forecasts/q1-2026-forecast.xlsx | F5: 15.01.2026 | G5: Capacity Planning Team | H5: Verified

Sheet Summary Dashboard
A1: CAPACITY FORECASTS AND PLANNING — SUMMARY DASHBOARD
A2: Consolidated capacity forecasting and planning effectiveness across all assessment areas.
A4: TABLE 1 — ASSESSMENT AREA COMPLIANCE
A5: Assessment Area | B5: Total Items | C5: Compliant | D5: Partial | E5: Non-Compliant | F5: N/A | G5: Compliance %
A6: Capacity Forecasts (Confidence) | B6: =C6+D6+E6+F6 | C6: =COUNTIF('Capacity Forecasts'!G5:G54,"High") | D6: =COUNTIF('Capacity Forecasts'!G5:G54,"Medium") | E6: =COUNTIF('Capacity Forecasts'!G5:G54,"Low") | F6: =0 | G6: =IF((B6-F6)=0,0,C6/(B6-F6))
A7: Expansion Approval Status | B7: =C7+D7+E7+F7 | C7: =COUNTIF('Planned Expansions'!I5:I54,"Approved") | D7: =COUNTIF('Planned Expansions'!I5:I54,"Pending") | E7: =COUNTIF('Planned Expansions'!I5:I54,"Rejected") | F7: =COUNTIF('Planned Expansions'!I5:I54,"Deferred") | G7: =IF((B7-F7)=0,0,C7/(B7-F7))
A8: Expansion Implementation Status | B8: =C8+D8+E8+F8 | C8: =COUNTIF('Planned Expansions'!G5:G54,"Completed") | D8: =COUNTIF('Planned Expansions'!G5:G54,"In Procurement")+COUNTIF('Planned Expansions'!G5:G54,"Ordered")+COUNTIF('Planned Expansions'!G5:G54,"Delivered")+COUNTIF('Planned Expansions'!G5:G54,"Installed") | E8: =COUNTIF('Planned Expansions'!G5:G54,"Planned") | F8: =COUNTIF('Planned Expansions'!G5:G54,"Cancelled") | G8: =IF((B8-F8)=0,0,C8/(B8-F8))
A9: Forecast Accuracy | B9: =C9+D9+E9+F9 | C9: =COUNTIF('Forecast Accuracy'!G5:G54,"Excellent")+COUNTIF('Forecast Accuracy'!G5:G54,"Good") | D9: =COUNTIF('Forecast Accuracy'!G5:G54,"Acceptable") | E9: =COUNTIF('Forecast Accuracy'!G5:G54,"Poor") | F9: =0 | G9: =IF((B9-F9)=0,0,C9/(B9-F9))
A10: Budget Approval Status | B10: =C10+D10+E10+F10 | C10: =COUNTIF('Budget Planning'!F5:F54,"Approved") | D10: =COUNTIF('Budget Planning'!F5:F54,"Pending") | E10: =COUNTIF('Budget Planning'!F5:F54,"Rejected") | F10: =COUNTIF('Budget Planning'!F5:F54,"Deferred") | G10: =IF((B10-F10)=0,0,C10/(B10-F10))
A12: TABLE 2 — KEY PERFORMANCE INDICATORS
A13: KPI Metric | B13: Value
A14: Historical Records Entered | B14: =COUNTA('Historical Utilization'!A5:A54)
A15: Resources with Growth Trends Documented | B15: =COUNTA('Trend Analysis'!A5:A54)
A16: High Confidence Forecasts Rate | B16: =IFERROR(COUNTIF('Capacity Forecasts'!G5:G54,"High")/COUNTA('Capacity Forecasts'!G5:G54),0)
A17: Resources with Critical Exhaustion Risk | B17: =COUNTIF('Capacity Exhaustion'!G5:G54,"CRITICAL")
A18: Resources with Immediate Exhaustion Risk (0–3 months) | B18: =COUNTIF('Capacity Exhaustion'!G5:G54,"Immediate (0-3mo)")
A19: Planned Expansions Approved | B19: =COUNTIF('Planned Expansions'!I5:I54,"Approved")
A20: Forecast Accuracy — Excellent/Good | B20: =COUNTIF('Forecast Accuracy'!G5:G54,"Excellent")+COUNTIF('Forecast Accuracy'!G5:G54,"Good")
A21: Budget Items Approved | B21: =COUNTIF('Budget Planning'!F5:F54,"Approved")
A23: TABLE 3 — CRITICAL EXHAUSTION RISKS (CRITICAL OR IMMEDIATE 0–3 MONTHS)
A24: Resource Name | B24: Current (%) | C24: Threshold (%) | D24: Months to Threshold | E24: Exhaustion Date | F24: Urgency | G24: Action Required
A37: Total Critical/Immediate Exhaustion Risks: | B37: =COUNTIF('Capacity Exhaustion'!G5:G54,"CRITICAL")+COUNTIF('Capacity Exhaustion'!G5:G54,"Immediate (0-3mo)")

Sheet Approval Sign-Off
A1: ASSESSMENT APPROVAL AND SIGN-OFF
A2: ISO/IEC 27001:2022 - Control A.8.6: Capacity Management
A3: ASSESSMENT SUMMARY
A4: Document: | B4: ISMS-IMP-A.8.6-Assessment-2 - Capacity Forecasting & Planning
A5: Assessment Period:
A6: Overall Compliance Rating: | B6: =IFERROR(AVERAGE('Summary Dashboard'!G6:G10),"")
A7: Assessment Status:
A8: Assessed By:
A11: COMPLETED BY (ASSESSOR)
A12: Name:
A13: Title:
A14: Date:
A15: Signature:
A16: Comments:
A18: REVIEWED BY (INFORMATION SECURITY OFFICER)
A19: Name:
A20: Title:
A21: Date:
... A38: Special Considerations:
