Workbook

Sheet Instructions & Legend
A1: ISMS-IMP-A.5.23.S1 - Cloud Service Inventory & Classification ISO/IEC 27001:2022 - Control A.5.19-23: Information Security for Use of Cloud Services
A3: Document Information
A4: Document ID | B4: ISMS-IMP-A.5.23.S1
A5: Workbook Title | B5: Cloud Service Inventory & Classification
A6: Control Reference | B6: ISO/IEC 27001:2022 - Control A.5.19-23: Information Security for Use of Cloud Services
A7: Version | B7: 1.0
A8: Assessment Date
A9: Completed By
A10: Organisation
A12: Instructions
A13: 1. Complete each assessment sheet for all cloud services in your inventory.
A14: 2. Use dropdown menus for standardised entries.
A15: 3. Fill in yellow-highlighted cells with your service-specific information.
A16: 4. Complete regulatory columns (Y-AG) for DORA/NIS2/AI Act/CLOUD Act as applicable.
A17: 5. Provide evidence location for each inventory entry.
A18: 6. Classify each service by deployment model, data sensitivity, and business criticality.
A19: 7. Update the inventory when cloud services are added, changed, or decommissioned.
A20: 8. Summary Dashboard auto-calculates compliance statistics.
... A24: Status Legend
A25: Symbol | B25: Status | C25: Description
A26: ✓ | B26: Compliant / Complete | C26: Requirement fully met
A27: ⚠ | B27: Partial / In Progress | C27: Partially met or in progress
A28: ✗ | B28: Non-Compliant / Not Started | C28: Requirement not met
A29: — | B29: Not Applicable | C29: Not applicable to this assessment
A31: Regulatory Compliance
A32: This workbook includes regulatory compliance tracking for:
A33: • DORA (Digital Operational Resilience Act) — EU financial entity requirements
A34: • NIS2 (Network and Information Security Directive 2) — Essential/important entities
A35: • EU AI Act — AI system classification and provider evaluation
A36: • US CLOUD Act — Jurisdictional risk for US-headquartered providers
A38: Regulatory columns (Y–AG) are included in each assessment sheet.
A39: Complete only the regulatory sections applicable to your organisation.
A41: Acceptable Evidence (examples)
A42: ✓ Cloud service contracts and terms of service
A43: ✓ Data Processing Agreement (DPA) / Addendum
A44: ✓ Service Level Agreement (SLA)
... A56: ✓ Jurisdictional risk assessment (for US-nexus providers)

Sheet 2. SaaS Services
A1: SAAS SERVICES INVENTORY All SaaS applications must be documented with data classification (Policy S5 Section 2.1)
A2: SaaS Services | Inventory and regulatory assessment of all Software-as-a-Service applications (DORA / NIS2 / AI Act / CLOUD Act)
A3: Does your organisation use SaaS applications?
A4: Response:
A6: Cloud Service Name | B6: Service Type | C6: Vendor Name | D6: Service Criticality | E6: Data Classification | F6: Data Residency | G6: Contract Status | H6: Status | I6: Evidence Location | J6: Gap Description | K6: Remediation Needed | L6: Exception ID | M6: Risk ID | N6: Compensating Controls | O6: Service Owner | P6: Target Remediation Date | Q6: Budget Impact | R6: Monthly Cost CHF | S6: Annual Contract Value | T6: Licensed Users | U6: Integration Count | V6: Backup Available | W6: Exit Feasibility | X6: Last Review Date | Y6: Provider HQ Jurisdiction | Z6: CLOUD Act Exposure | AA6: Data Processing Locations | AB6: EU Data Boundary | AC6: DORA In Scope | AD6: NIS2 In Scope | AE6: AI Classification | AF6: Concentration Risk | AG6: Alternatives Identified
A8: Example: Microsoft 365 | B8: SaaS | C8: Microsoft | D8: Critical | H8: ✅ Compliant | Y8: United States | Z8: Mitigated (EU Data Boundary) | AC8: Yes | AD8: Yes | AF8: High (Few alternatives)
A61: COMPLIANCE CHECKLIST
A63: Item | B63: Requirement | C63: Status | D63: Evidence
A64: ☐ | B64: All cloud services documented in CMDB | D64: CMDB export
A65: ☐ | B65: Data classification assigned | D65: Data classification matrix
A66: ☐ | B66: Service criticality assessed (BIA) | D66: Business impact analysis
A67: ☐ | B67: Service owner identified | D67: RACI matrix
A68: ☐ | B68: Contract status tracked | D68: Contract management system
A69: ☐ | B69: Monthly costs documented | D69: Finance system
A70: ☐ | B70: User license count verified | D70: License report
A71: ☐ | B71: Integration dependencies mapped | D71: Architecture diagram
A72: ☐ | B72: Backup strategy defined | D72: BC/DR plan
A73: ☐ | B73: Exit feasibility evaluated | D73: Exit strategy document
A74: ☐ | B74: Data residency verified | D74: Vendor DPA
A75: ☐ | B75: Last review date recorded | D75: Review calendar
... A83: ☐ | B83: Alternative providers identified | D83: Market analysis

Sheet 3. IaaS PaaS Services
A1: IAAS/PAAS SERVICES INVENTORY All infrastructure services must maintain security baselines (Policy S5 Section 2.2)
A2: IaaS/PaaS Services | Inventory and regulatory assessment of infrastructure and platform cloud services
A3: Does your organisation use IaaS or PaaS services?
A4: Response:
A6: Cloud Service Name | B6: Service Type | C6: Vendor Name | D6: Service Criticality | E6: Data Classification | F6: Data Residency | G6: Contract Status | H6: Status | I6: Evidence Location | J6: Gap Description | K6: Remediation Needed | L6: Exception ID | M6: Risk ID | N6: Compensating Controls | O6: Service Owner | P6: Target Remediation Date | Q6: Budget Impact | R6: Monthly Cost CHF | S6: Annual Contract Value | T6: Licensed Users | U6: Integration Count | V6: Backup Available | W6: Exit Feasibility | X6: Last Review Date | Y6: Provider HQ Jurisdiction | Z6: CLOUD Act Exposure | AA6: Data Processing Locations | AB6: EU Data Boundary | AC6: DORA In Scope | AD6: NIS2 In Scope | AE6: AI Classification | AF6: Concentration Risk | AG6: Alternatives Identified
A8: Example: Microsoft 365 | B8: SaaS | C8: Microsoft | D8: Critical | H8: ✅ Compliant | Y8: United States | Z8: Mitigated (EU Data Boundary) | AC8: Yes | AD8: Yes | AF8: High (Few alternatives)
A61: COMPLIANCE CHECKLIST
A63: Item | B63: Requirement | C63: Status | D63: Evidence
A64: ☐ | B64: All cloud services documented in CMDB | D64: CMDB export
A65: ☐ | B65: Data classification assigned | D65: Data classification matrix
A66: ☐ | B66: Service criticality assessed (BIA) | D66: Business impact analysis
A67: ☐ | B67: Service owner identified | D67: RACI matrix
A68: ☐ | B68: Contract status tracked | D68: Contract management system
A69: ☐ | B69: Monthly costs documented | D69: Finance system
A70: ☐ | B70: User license count verified | D70: License report
A71: ☐ | B71: Integration dependencies mapped | D71: Architecture diagram
A72: ☐ | B72: Backup strategy defined | D72: BC/DR plan
A73: ☐ | B73: Exit feasibility evaluated | D73: Exit strategy document
A74: ☐ | B74: Data residency verified | D74: Vendor DPA
A75: ☐ | B75: Last review date recorded | D75: Review calendar
... A83: ☐ | B83: Alternative providers identified | D83: Market analysis

Sheet 4. Cloud Security Services
A1: SHEET 4: EXIT FEASIBILITY & STRATEGY ASSESSMENT
A2: POL-S5 Section 8.1.1: Cloud-to-Cloud (90%+), Hybrid (5-10%), On-Premises (<5% only when justified)
A3: Service Name | B3: Provider | C3: Service Type | D3: Environment | E3: Business Owner | F3: Technical Owner | G3: Data Classification | H3: Criticality | I3: Users | J3: Cost (Annual CHF) | K3: Contract End Date | L3: Primary Region | M3: Backup Region | N3: Integration Count | O3: API Dependency | P3: Compliance Certs | Q3: Current Status | R3: Exit Strategy Type | S3: Alternative Identified | T3: Export Format Available | U3: Export Tested | V3: Data Volume (GB) | W3: Migration Complexity | X3: Lock-In Risk | Y3: Hybrid: Workload Segmentation | Z3: Hybrid: Data Sync Latency | AA3: OnPrem: TCO Analysis Complete | AB3: OnPrem: Infrastructure Available | AC3: OnPrem: Staffing Plan Documented
A4: Microsoft 365 | B4: Microsoft | C4: SaaS | D4: Production | E4: IT Director | F4: Cloud Admin | G4: Confidential | H4: Critical | I4: 250 | J4: 125000 | K4: 31.12.2026 | L4: West Europe (Amsterdam) | M4: North Europe (Dublin) | N4: 15 | O4: Yes | P4: ISO 27001, SOC 2 Type II | Q4: ✅ Compliant | R4: Cloud-to-Cloud | S4: Cloud Provider (GCP) | T4: Standard (CSV/JSON) | U4: Yes | V4: 2500 | W4: Cloud-to-Cloud (Medium) | X4: Medium | Y4: Not Applicable | Z4: Not Applicable | AA4: N/A | AB4: N/A | AC4: N/A
A57: EXIT STRATEGY COMPLIANCE CHECKLIST (22 items)
A106: 1. ✅ Exit strategy documented for Critical/High services
A107: 2. ✅ Exit triggers defined
A108: 3. ✅ Alternative providers/solutions identified
A109: 4. ✅ Alternative provider assessment completed
A110: 5. ✅ Migration effort estimated
A111: 6. ✅ Data extraction requirements documented
A112: 7. ✅ Application dependencies mapped
A113: 8. ✅ Integration points documented
A114: 9. ✅ Lock-in risks identified and documented
A115: 10. ✅ Exit cost estimate completed
A116: 11. ✅ Exit timeline estimate completed
... A173: • POL-S5 Section 8.1.1.3 (On-Premises)

Sheet 5. Cloud Storage Services
A1: CLOUD STORAGE SERVICES INVENTORY All cloud storage must enforce encryption (Policy S5 Section 2.4)
A2: Cloud Storage Services | Inventory and regulatory assessment of cloud storage and object store solutions
A3: Does your organisation use cloud storage services?
A4: Response:
A6: Cloud Service Name | B6: Service Type | C6: Vendor Name | D6: Service Criticality | E6: Data Classification | F6: Data Residency | G6: Contract Status | H6: Status | I6: Evidence Location | J6: Gap Description | K6: Remediation Needed | L6: Exception ID | M6: Risk ID | N6: Compensating Controls | O6: Service Owner | P6: Target Remediation Date | Q6: Budget Impact | R6: Monthly Cost CHF | S6: Annual Contract Value | T6: Licensed Users | U6: Integration Count | V6: Backup Available | W6: Exit Feasibility | X6: Last Review Date | Y6: Provider HQ Jurisdiction | Z6: CLOUD Act Exposure | AA6: Data Processing Locations | AB6: EU Data Boundary | AC6: DORA In Scope | AD6: NIS2 In Scope | AE6: AI Classification | AF6: Concentration Risk | AG6: Alternatives Identified
A8: Example: Microsoft 365 | B8: SaaS | C8: Microsoft | D8: Critical | H8: ✅ Compliant | Y8: United States | Z8: Mitigated (EU Data Boundary) | AC8: Yes | AD8: Yes | AF8: High (Few alternatives)
A61: COMPLIANCE CHECKLIST
A63: Item | B63: Requirement | C63: Status | D63: Evidence
A64: ☐ | B64: All cloud services documented in CMDB | D64: CMDB export
A65: ☐ | B65: Data classification assigned | D65: Data classification matrix
A66: ☐ | B66: Service criticality assessed (BIA) | D66: Business impact analysis
A67: ☐ | B67: Service owner identified | D67: RACI matrix
A68: ☐ | B68: Contract status tracked | D68: Contract management system
A69: ☐ | B69: Monthly costs documented | D69: Finance system
A70: ☐ | B70: User license count verified | D70: License report
A71: ☐ | B71: Integration dependencies mapped | D71: Architecture diagram
A72: ☐ | B72: Backup strategy defined | D72: BC/DR plan
A73: ☐ | B73: Exit feasibility evaluated | D73: Exit strategy document
A74: ☐ | B74: Data residency verified | D74: Vendor DPA
A75: ☐ | B75: Last review date recorded | D75: Review calendar
... A83: ☐ | B83: Alternative providers identified | D83: Market analysis

Sheet 6. Data Classification
A1: DATA CLASSIFICATION - CLOUD STORAGE INVENTORY
A2: Classify all data types stored in cloud services. Required for ISO 27001 A.5.12 (Classification), A.5.13 (Labelling), and GDPR Article 30.
A3: Data ID | B3: Data Category | C3: Description | D3: Classification Level | E3: Primary Cloud Service | F3: Storage Location | G3: Data Owner | H3: Retention Period | I3: Personal Data (GDPR) | J3: Cross-Border Transfer
A4: DC-001 | B4: Customer PII | C4: Customer names, email addresses, phone numbers in CRM system | D4: Confidential | E4: AWS S3 | F4: eu-west-1 (Ireland) | G4: VP Sales | H4: 7 years post-contract | I4: Yes - Personal | J4: EEA Only

Sheet 7. Service Criticality
A1: SERVICE CRITICALITY ASSESSMENT
A2: Assess criticality of each cloud service for BIA and exit strategy planning. Required for ISO 27001 A.5.29 (Business Continuity) and DORA Article 28.
A3: Service ID | B3: Cloud Service Name | C3: Service Category | D3: Business Process Supported | E3: Criticality Level | F3: RTO (Hours) | G3: RPO (Hours) | H3: MTPD (Hours) | I3: Single Point of Failure | J3: Workaround Available | K3: DORA Scope | L3: Exit Priority
A4: SC-001 | B4: Microsoft 365 (Email, SharePoint, Teams) | C4: SaaS | D4: Email communication, document collaboration, internal comms | E4: Critical | F4: 4 | G4: 1 | H4: 8 | I4: Yes | J4: Partial | K4: In-Scope | L4: P1 - Critical

Sheet Evidence Register
A1: EVIDENCE REGISTER
A2: List all evidence files/documents referenced in this assessment (audit traceability).
A4: Evidence ID | B4: Assessment Area | C4: Evidence Type | D4: Description | E4: Location/Path | F4: Date Collected | G4: Collected By | H4: Verification Status
A5: EV-001 | B5: Cloud Service Inventory | C5: CMDB Export | D5: Complete inventory of all SaaS/IaaS/PaaS services with vendor details | E5: /evidence/cloud-inventory-q1-2026.xlsx | F5: 15.01.2026 | G5: IT Security Team | H5: Verified

Sheet Summary Dashboard
A1: CLOUD SERVICE INVENTORY — SUMMARY DASHBOARD
A2: ISO/IEC 27001:2022 - Control A.5.19-23: Information Security for Use of Cloud Services
A3: TABLE 1: COMPLIANCE BY SERVICE CATEGORY
A4: Category | B4: Total | C4: ✅ Compliant | D4: ⚠ Partial | E4: ❌ Non-Compliant | F4: N/A | G4: Compliance %
A5: SaaS Services | B5: =COUNTA('2. SaaS Services'!A9:A100) | C5: =COUNTIF('2. SaaS Services'!H9:H100,"✅*") | D5: =COUNTIF('2. SaaS Services'!H9:H100,"⚠*") | E5: =COUNTIF('2. SaaS Services'!H9:H100,"❌*") | F5: =COUNTIF('2. SaaS Services'!H9:H100,"N/A") | G5: =IF((B5-F5)=0,"0%",ROUND(C5/(B5-F5)*100,1)&"%")
A6: IaaS/PaaS | B6: =COUNTA('3. IaaS PaaS Services'!A9:A100) | C6: =COUNTIF('3. IaaS PaaS Services'!H9:H100,"✅*") | D6: =COUNTIF('3. IaaS PaaS Services'!H9:H100,"⚠*") | E6: =COUNTIF('3. IaaS PaaS Services'!H9:H100,"❌*") | F6: =COUNTIF('3. IaaS PaaS Services'!H9:H100,"N/A") | G6: =IF((B6-F6)=0,"0%",ROUND(C6/(B6-F6)*100,1)&"%")
A7: Storage Services | B7: =COUNTA('5. Cloud Storage Services'!A9:A100) | C7: =COUNTIF('5. Cloud Storage Services'!H9:H100,"✅*") | D7: =COUNTIF('5. Cloud Storage Services'!H9:H100,"⚠*") | E7: =COUNTIF('5. Cloud Storage Services'!H9:H100,"❌*") | F7: =COUNTIF('5. Cloud Storage Services'!H9:H100,"N/A") | G7: =IF((B7-F7)=0,"0%",ROUND(C7/(B7-F7)*100,1)&"%")
A8: TOTAL | B8: =SUM(B5:B7) | C8: =SUM(C5:C7) | D8: =SUM(D5:D7) | E8: =SUM(E5:E7) | F8: =SUM(F5:F7) | G8: =IF(B8-F8>0,ROUND(C8/(B8-F8)*100,1)&"%","N/A")
A11: TABLE 2: REGULATORY COMPLIANCE SUMMARY (DORA / NIS2 / AI Act / CLOUD Act)
A13: Metric | B13: Count | C13: Status
A14: CLOUD Act Potential Exposure | B14: =COUNTIF('2. SaaS Services'!Z9:Z100,"Potential*")+COUNTIF('3. IaaS PaaS Services'!Z9:Z100,"Potential*") | C14: =IF(B14>0,"⚠ Review","✅ OK")
A15: DORA In-Scope Services | B15: =COUNTIF('2. SaaS Services'!AC9:AC100,"Yes")+COUNTIF('3. IaaS PaaS Services'!AC9:AC100,"Yes") | C15: =IF(B15>0,"⚠ Review","✅ OK")
A16: NIS2 In-Scope Services | B16: =COUNTIF('2. SaaS Services'!AD9:AD100,"Yes")+COUNTIF('3. IaaS PaaS Services'!AD9:AD100,"Yes") | C16: =IF(B16>0,"⚠ Review","✅ OK")
A17: High-Risk AI Systems | B17: =COUNTIF('2. SaaS Services'!AE9:AE100,"High Risk")+COUNTIF('3. IaaS PaaS Services'!AE9:AE100,"High Risk") | C17: =IF(B17>0,"⚠ Review","✅ OK")
A18: Critical Concentration Risk | B18: =COUNTIF('2. SaaS Services'!AF9:AF100,"Critical*")+COUNTIF('3. IaaS PaaS Services'!AF9:AF100,"Critical*") | C18: =IF(B18>0,"⚠ Review","✅ OK")

Sheet Approval Sign-Off
A1: ASSESSMENT APPROVAL AND SIGN-OFF
A2: ISO/IEC 27001:2022 - Control A.5.19-23: Information Security for Use of Cloud Services
A3: ASSESSMENT SUMMARY
A4: Document: | B4: ISMS-IMP-A.5.23.S1 - Cloud Service Inventory & Classification
A5: Assessment Period:
A6: Overall Compliance Rating: | B6: =IFERROR(AVERAGE('Summary Dashboard'!G6:G7),"")
A7: Assessment Status:
A8: Assessed By:
A11: COMPLETED BY (ASSESSOR)
A12: Name:
A13: Title:
A14: Date:
A15: Signature:
A16: Comments:
A18: REVIEWED BY (INFORMATION SECURITY OFFICER)
A19: Name:
A20: Title:
A21: Date:
... A38: Special Considerations:
