Workbook

Sheet Executive_Summary
A1: Threat Intelligence Program - Executive Summary
A2: Reporting Period: February 2026 | E2: Generated: 08.02.2026 | I2: Classification: INTERNAL
A4: PROGRAM HEALTH SCORE | F4: Intelligence Production | I4: Stakeholder Satisfaction | K4: IOC Effectiveness
F5: =COUNTIF('[ISMS-IMP-A.5.7.2.xlsx]Intelligence_Production'!N:N,"Published") | I5: =AVERAGE('[ISMS-IMP-A.5.7.2.xlsx]Intelligence_Production'!J:J) | K5: =COUNTA('[ISMS-IMP-A.5.7.3.xlsx]IOC_Deployment'!A:A)-4
F7: Products This Month | I7: Avg Rating (1-5) | K7: IOCs Deployed
A8: =AVERAGE(Program_KPIs!E5:E24)
A11: Scale: 1.0 (Critical) → 5.0 (Excellent)
A14: INTEGRATION STATUS | F14: CONTROL 8.8 LINKAGE (VTL) | I14: COMPLIANCE STATUS
A15: Security Tools Integrated: | C15: =COUNTA('[ISMS-IMP-A.5.7.3.xlsx]Tool_Integration_Matrix'!A:A)-4 | F15: Total VT Links: | H15: =COUNTA('[ISMS-IMP-A.5.7.2.xlsx]Vulnerability_Linked_Threats'!A:A)-4 | I15: ISO 27001:2022 Control 5.7: | L15: =COUNTIF(Compliance_Evidence!F:F,"Current")/COUNTA(Compliance_Evidence!A:A)-4
A16: Fully Integrated: | C16: =COUNTIF('[ISMS-IMP-A.5.7.3.xlsx]Tool_Integration_Matrix'!D:D,"Full") | F16: Active Exploitation: | H16: =COUNTIF('[ISMS-IMP-A.5.7.2.xlsx]Vulnerability_Linked_Threats'!E:E,"Active_Exploitation") | I16: Outstanding Evidence: | L16: =COUNTIF(Compliance_Evidence!F:F,"Missing")
A17: Partially Integrated: | C17: =COUNTIF('[ISMS-IMP-A.5.7.3.xlsx]Tool_Integration_Matrix'!D:D,"Partial") | F17: Patched: | H17: =COUNTIF('[ISMS-IMP-A.5.7.2.xlsx]Vulnerability_Linked_Threats'!R:R,"Patched") | I17: Next Audit: | L17: [Enter Date]
A22: 📊 VISUALIZATION AREAS (Add charts manually or via reporting tools)
A23: Area 1 (A23:D30): Source Performance Trend Chart (6 months)
A24: Area 2 (E23:H30): Intelligence Production Volume (bar chart)
A25: Area 3 (I23:L30): Stakeholder Satisfaction Trend (line chart)
A26: Area 4 (A31:F38): MITRE ATT&CK Coverage Heat Map
A27: Area 5 (G31:L38): Risk Indicator Dashboard (gauges)
A40: ⚠️ EXTERNAL REFERENCE SETUP REQUIRED ⚠️ This dashboard uses external references to aggregate data from: - ISMS-IMP-A.5.7.1 (Threat Intelligence Sources) - ISMS-IMP-A.5.7.2 (Collection & Analysis) - ISMS-IMP-A.5.7.3 (Integration & Distribution) AFTER GENERATION, you must: 1. Place all 5.7 workbooks in the same directory 2. Open this dashboard workbook 3. Go to Data → Edit Links (or Data → Connections) 4. Update source file paths to match your directory structure Example paths to update: [ISMS-IMP-A.5.7.1.xlsx]Source_Inventory!A:B [ISMS-IMP-A.5.7.2.xlsx]Intelligence_Production!A:C [ISMS-IMP-A.5.7.3.xlsx]IOC_Deployment!A:T When opening this file, Excel will prompt: "Update Links?" → Click UPDATE. For formulas with external references, see Program_KPIs sheet column "Data_Source".

Sheet Program_KPIs
A1: Threat Intelligence Program - Key Performance Indicators
A2: Track program KPIs with targets and thresholds. Set target values based on organizational goals.
A4: KPI ID | B4: KPI Category | C4: KPI Name | D4: Description | E4: Unit | F4: Measurement Frequency | G4: Data Source | H4: Target Value | I4: Warning Threshold | J4: Critical Threshold | K4: Current Value | L4: Last Month Value | M4: Performance vs Target | N4: Status | O4: Trend | P4: Owner | Q4: Last Updated | R4: Notes
A5: KPI-TI-001 | B5: Source_Management | C5: Number of Active Sources | D5: Count of active TI sources | E5: Count | F5: Monthly | G5: =[ISMS-IMP-A.5.7.1.xlsx]Source_Inventory!B:B | H5: 20 | I5: 16 | J5: 12 | M5: =IF(OR(K5="",H5=""),"N/A",(K5/H5-1)*100) | N5: =IF(K5="","N/A",IF(K5>=H5,"On_Track",IF(K5>=I5,"Caution","At_Risk"))) | O5: =IF(OR(K5="",L5=""),"N/A",IF(K5>L5,"Improving",IF(K5<L5,"Declining","Stable")))
A6: KPI-TI-002 | B6: Source_Management | C6: Average Source Quality Score | D6: Avg Admiralty Code score | E6: Score (1-5) | F6: Monthly | G6: =[ISMS-IMP-A.5.7.1.xlsx]Source_Evaluation!H:H | H6: 4.0 | I6: 3.5 | J6: 3.0 | M6: =IF(OR(K6="",H6=""),"N/A",(K6/H6-1)*100) | N6: =IF(K6="","N/A",IF(K6>=H6,"On_Track",IF(K6>=I6,"Caution","At_Risk"))) | O6: =IF(OR(K6="",L6=""),"N/A",IF(K6>L6,"Improving",IF(K6<L6,"Declining","Stable")))
A7: KPI-TI-003 | B7: Source_Management | C7: Source Coverage Gaps | D7: Requirements with inadequate coverage | E7: Count | F7: Monthly | G7: =[ISMS-IMP-A.5.7.1.xlsx]Coverage_Matrix!Summary | H7: 5 | I7: 8 | J7: 12 | M7: =IF(OR(K7="",H7=""),"N/A",(K7/H7-1)*100) | N7: =IF(K7="","N/A",IF(K7>=H7,"On_Track",IF(K7>=I7,"Caution","At_Risk"))) | O7: =IF(OR(K7="",L7=""),"N/A",IF(K7>L7,"Improving",IF(K7<L7,"Declining","Stable")))
A8: KPI-TI-004 | B8: Source_Management | C8: Cost Per Source (Avg) | D8: Average annual cost per source | E8: USD | F8: Quarterly | G8: =[ISMS-IMP-A.5.7.1.xlsx]Cost_Analysis!E:E | H8: 50000 | I8: 60000 | J8: 75000 | M8: =IF(OR(K8="",H8=""),"N/A",(K8/H8-1)*100) | N8: =IF(K8="","N/A",IF(K8>=H8,"On_Track",IF(K8>=I8,"Caution","At_Risk"))) | O8: =IF(OR(K8="",L8=""),"N/A",IF(K8>L8,"Improving",IF(K8<L8,"Declining","Stable")))
A9: KPI-TI-005 | B9: Production | C9: Intelligence Products per Month | D9: Count of published products | E9: Reports | F9: Monthly | G9: =COUNTIF('[ISMS-IMP-A.5.7.2.xlsx]Intelligence_Production'!N:N,"Published") | H9: 20 | I9: 16 | J9: 12 | M9: =IF(OR(K9="",H9=""),"N/A",(K9/H9-1)*100) | N9: =IF(K9="","N/A",IF(K9>=H9,"On_Track",IF(K9>=I9,"Caution","At_Risk"))) | O9: =IF(OR(K9="",L9=""),"N/A",IF(K9>L9,"Improving",IF(K9<L9,"Declining","Stable")))
A10: KPI-TI-006 | B10: Analysis | C10: Avg Time to Produce (hours) | D10: Hours from start to publication | E10: Hours | F10: Monthly | G10: =AVERAGE('[ISMS-IMP-A.5.7.2.xlsx]Intelligence_Production'!M:M) | H10: 48 | I10: 72 | J10: 96 | M10: =IF(OR(K10="",H10=""),"N/A",(K10/H10-1)*100) | N10: =IF(K10="","N/A",IF(K10>=H10,"On_Track",IF(K10>=I10,"Caution","At_Risk"))) | O10: =IF(OR(K10="",L10=""),"N/A",IF(K10>L10,"Improving",IF(K10<L10,"Declining","Stable")))
A11: KPI-TI-007 | B11: Production | C11: Stakeholder Feedback Rating | D11: Average consumer rating | E11: Rating (1-5) | F11: Monthly | G11: =AVERAGE('[ISMS-IMP-A.5.7.2.xlsx]Intelligence_Production'!J:J) | H11: 4.0 | I11: 3.5 | J11: 3.0 | M11: =IF(OR(K11="",H11=""),"N/A",(K11/H11-1)*100) | N11: =IF(K11="","N/A",IF(K11>=H11,"On_Track",IF(K11>=I11,"Caution","At_Risk"))) | O11: =IF(OR(K11="",L11=""),"N/A",IF(K11>L11,"Improving",IF(K11<L11,"Declining","Stable")))
A12: KPI-TI-008 | B12: Production | C12: Intelligence Consumption Rate | D12: % of products acted upon | E12: Percentage | F12: Monthly | G12: =AVERAGE('[ISMS-IMP-A.5.7.2.xlsx]Intelligence_Production'!K:K) | H12: 75% | I12: 60% | J12: 50% | M12: =IF(OR(K12="",H12=""),"N/A",(K12/H12-1)*100) | N12: =IF(K12="","N/A",IF(K12>=H12,"On_Track",IF(K12>=I12,"Caution","At_Risk"))) | O12: =IF(OR(K12="",L12=""),"N/A",IF(K12>L12,"Improving",IF(K12<L12,"Declining","Stable")))
A13: KPI-TI-009 | B13: Analysis | C13: MITRE ATT&CK Coverage | D13: % of critical techniques covered | E13: Percentage | F13: Quarterly | G13: =COUNTIF('[ISMS-IMP-A.5.7.2.xlsx]MITRE_Mapping'!F:F,"Full")/COUNTA('[ISMS-IMP-A.5.7.2.xlsx]MITRE_Mapping'!A:A)-4 | H13: 80% | I13: 70% | J13: 60% | M13: =IF(OR(K13="",H13=""),"N/A",(K13/H13-1)*100) | N13: =IF(K13="","N/A",IF(K13>=H13,"On_Track",IF(K13>=I13,"Caution","At_Risk"))) | O13: =IF(OR(K13="",L13=""),"N/A",IF(K13>L13,"Improving",IF(K13<L13,"Declining","Stable")))
A14: KPI-TI-010 | B14: Analysis | C14: Analyst Training Completion | D14: % of planned training completed | E14: Percentage | F14: Quarterly | G14: =AVERAGE('[ISMS-IMP-A.5.7.2.xlsx]Analyst_Capabilities'!J:J) | H14: 90% | I14: 75% | J14: 60% | M14: =IF(OR(K14="",H14=""),"N/A",(K14/H14-1)*100) | N14: =IF(K14="","N/A",IF(K14>=H14,"On_Track",IF(K14>=I14,"Caution","At_Risk"))) | O14: =IF(OR(K14="",L14=""),"N/A",IF(K14>L14,"Improving",IF(K14<L14,"Declining","Stable")))
A15: KPI-TI-011 | B15: Collection | C15: VT Links Created per Month | D15: Vulnerability-threat linkages | E15: Count | F15: Monthly | G15: =COUNTA('[ISMS-IMP-A.5.7.2.xlsx]Vulnerability_Linked_Threats'!A:A)-4 | H15: 10 | I15: 7 | J15: 5 | M15: =IF(OR(K15="",H15=""),"N/A",(K15/H15-1)*100) | N15: =IF(K15="","N/A",IF(K15>=H15,"On_Track",IF(K15>=I15,"Caution","At_Risk"))) | O15: =IF(OR(K15="",L15=""),"N/A",IF(K15>L15,"Improving",IF(K15<L15,"Declining","Stable")))
A16: KPI-TI-012 | B16: Integration | C16: Security Tools Integrated | D16: Tools with TI integration | E16: Count | F16: Quarterly | G16: =COUNTA('[ISMS-IMP-A.5.7.3.xlsx]Tool_Integration_Matrix'!A:A)-4 | H16: 15 | I16: 12 | J16: 10 | M16: =IF(OR(K16="",H16=""),"N/A",(K16/H16-1)*100) | N16: =IF(K16="","N/A",IF(K16>=H16,"On_Track",IF(K16>=I16,"Caution","At_Risk"))) | O16: =IF(OR(K16="",L16=""),"N/A",IF(K16>L16,"Improving",IF(K16<L16,"Declining","Stable")))
A17: KPI-TI-013 | B17: Integration | C17: IOCs Deployed per Month | D17: Indicators deployed to security tools | E17: Count | F17: Monthly | G17: =COUNTA('[ISMS-IMP-A.5.7.3.xlsx]IOC_Deployment'!A:A)-4 | H17: 100 | I17: 75 | J17: 50 | M17: =IF(OR(K17="",H17=""),"N/A",(K17/H17-1)*100) | N17: =IF(K17="","N/A",IF(K17>=H17,"On_Track",IF(K17>=I17,"Caution","At_Risk"))) | O17: =IF(OR(K17="",L17=""),"N/A",IF(K17>L17,"Improving",IF(K17<L17,"Declining","Stable")))
A18: KPI-TI-014 | B18: Integration | C18: IOC Hit Rate | D18: % of IOCs with detections | E18: Percentage | F18: Monthly | G18: =COUNTIF('[ISMS-IMP-A.5.7.3.xlsx]IOC_Deployment'!I:I,"Active")/COUNTA('[ISMS-IMP-A.5.7.3.xlsx]IOC_Deployment'!A:A)-4 | H18: 15% | I18: 10% | J18: 5% | M18: =IF(OR(K18="",H18=""),"N/A",(K18/H18-1)*100) | N18: =IF(K18="","N/A",IF(K18>=H18,"On_Track",IF(K18>=I18,"Caution","At_Risk"))) | O18: =IF(OR(K18="",L18=""),"N/A",IF(K18>L18,"Improving",IF(K18<L18,"Declining","Stable")))
A19: KPI-TI-015 | B19: Integration | C19: IOC False Positive Rate | D19: % of IOCs generating false positives | E19: Percentage | F19: Monthly | G19: =COUNTIF('[ISMS-IMP-A.5.7.3.xlsx]IOC_Deployment'!J:J,">0")/COUNTA('[ISMS-IMP-A.5.7.3.xlsx]IOC_Deployment'!A:A)-4 | H19: 5% | I19: 10% | J19: 15% | M19: =IF(OR(K19="",H19=""),"N/A",(K19/H19-1)*100) | N19: =IF(K19="","N/A",IF(K19>=H19,"On_Track",IF(K19>=I19,"Caution","At_Risk"))) | O19: =IF(OR(K19="",L19=""),"N/A",IF(K19>L19,"Improving",IF(K19<L19,"Declining","Stable")))
A20: KPI-TI-016 | B20: Dissemination | C20: Stakeholder Engagement Score | D20: Average engagement rating | E20: Rating (1-5) | F20: Monthly | G20: =AVERAGE('[ISMS-IMP-A.5.7.3.xlsx]Feedback_Collection'!D:D) | H20: 4.0 | I20: 3.5 | J20: 3.0 | M20: =IF(OR(K20="",H20=""),"N/A",(K20/H20-1)*100) | N20: =IF(K20="","N/A",IF(K20>=H20,"On_Track",IF(K20>=I20,"Caution","At_Risk"))) | O20: =IF(OR(K20="",L20=""),"N/A",IF(K20>L20,"Improving",IF(K20<L20,"Declining","Stable")))
A21: KPI-TI-017 | B21: Dissemination | C21: Distribution Reach | D21: % of target audience reached | E21: Percentage | F21: Monthly | G21: =COUNTA('[ISMS-IMP-A.5.7.3.xlsx]Distribution_Tracking'!A:A)/COUNTA('[ISMS-IMP-A.5.7.3.xlsx]Stakeholder_Registry'!A:A) | H21: 90% | I21: 75% | J21: 60% | M21: =IF(OR(K21="",H21=""),"N/A",(K21/H21-1)*100) | N21: =IF(K21="","N/A",IF(K21>=H21,"On_Track",IF(K21>=I21,"Caution","At_Risk"))) | O21: =IF(OR(K21="",L21=""),"N/A",IF(K21>L21,"Improving",IF(K21<L21,"Declining","Stable")))
A22: KPI-TI-018 | B22: Dissemination | C22: Mean Time to Action | D22: Hours from intel to action taken | E22: Hours | F22: Monthly | G22: =AVERAGE('[ISMS-IMP-A.5.7.3.xlsx]Distribution_Tracking'!TimeToAction) | H22: 24 | I22: 48 | J22: 72 | M22: =IF(OR(K22="",H22=""),"N/A",(K22/H22-1)*100) | N22: =IF(K22="","N/A",IF(K22>=H22,"On_Track",IF(K22>=I22,"Caution","At_Risk"))) | O22: =IF(OR(K22="",L22=""),"N/A",IF(K22>L22,"Improving",IF(K22<L22,"Declining","Stable")))
A23: KPI-CVSS-001 | B23: Framework_Currency | C23: CVSS 4.0 Adoption Rate | D23: % of VTL records using CVSS 4.0 | E23: Percentage | F23: Monthly | G23: =IF(COUNTA([ISMS-IMP-A.5.7.2.xlsx]Vulnerability_Threat_Link!A:A)-4=0,0,COUNTIF([ISMS-IMP-A.5.7.2.xlsx]Vulnerability_Threat_Link!E:E,"4.0")/(COUNTA([ISMS-IMP-A.5.7.2.xlsx]Vulnerability_Threat_Link!A:A)-4)*100) | H23: 75% | I23: 60% | J23: 50% | M23: =IF(OR(K23="",H23=""),"N/A",(K23/H23-1)*100) | N23: =IF(K23="","N/A",IF(K23>=H23,"On_Track",IF(K23>=I23,"Caution","At_Risk"))) | O23: =IF(OR(K23="",L23=""),"N/A",IF(K23>L23,"Improving",IF(K23<L23,"Declining","Stable")))
A24: KPI-CVSS-002 | B24: Quality_Assurance | C24: CVSS Accuracy Rate (All Sources) | D24: Average CVSS accuracy across all TI sources | E24: Percentage | F24: Monthly | G24: =IFERROR(AVERAGE([ISMS-IMP-A.5.7.1.xlsx]Source_Performance_Validation!O:O),0) | H24: 90% | I24: 85% | J24: 80% | M24: =IF(OR(K24="",H24=""),"N/A",(K24/H24-1)*100) | N24: =IF(K24="","N/A",IF(K24>=H24,"On_Track",IF(K24>=I24,"Caution","At_Risk"))) | O24: =IF(OR(K24="",L24=""),"N/A",IF(K24>L24,"Improving",IF(K24<L24,"Declining","Stable")))
A25: KPI-CVSS-003 | B25: Emergency_Response | C25: High CVSS + Active Exploitation (Open) | D25: Count of CVSS>=7.0 with active exploitation still unpatched | E25: Count | F25: Daily | G25: =SUMPRODUCT(([ISMS-IMP-A.5.7.2.xlsx]Vulnerability_Threat_Link!F:F>=7)*(([ISMS-IMP-A.5.7.2.xlsx]Vulnerability_Threat_Link!L:L="Active Exploitation")+([ISMS-IMP-A.5.7.2.xlsx]Vulnerability_Threat_Link!L:L="Mass Exploitation"))*([ISMS-IMP-A.5.7.2.xlsx]Vulnerability_Threat_Link!M:M="Open")) | H25: 0 | I25: 0 | J25: 1 | M25: =IF(OR(K25="",H25=""),"N/A",(K25/H25-1)*100) | N25: =IF(A25="KPI-CVSS-003",IF(K25="","N/A",IF(K25=0,"On_Track","At_Risk")),IF(K25="","N/A",IF(K25>=H25,"On_Track",IF(K25>=I25,"Caution","At_Risk")))) | O25: =IF(OR(K25="",L25=""),"N/A",IF(K25>L25,"Improving",IF(K25<L25,"Declining","Stable")))
A26: KPI-CVSS-004 | B26: Impact_Measurement | C26: Avg CVSS (Prevented Incidents) | D26: Average CVSS score of prevented incidents | E26: Score (0-10) | F26: Monthly | G26: =IFERROR(AVERAGE([ISMS-IMP-A.5.7.3.xlsx]Prevention_Tracking!F:F),0) | H26: N/A | I26: N/A | J26: N/A | M26: =IF(OR(K26="",H26=""),"N/A",(K26/H26-1)*100) | N26: =IF(K26="","N/A",IF(K26>=H26,"On_Track",IF(K26>=I26,"Caution","At_Risk"))) | O26: =IF(OR(K26="",L26=""),"N/A",IF(K26>L26,"Improving",IF(K26<L26,"Declining","Stable")))
A27: KPI-RISK-001 | B27: Risk_Management | C27: Risk Updates with CVSS Quantification | D27: % of vulnerability risks with CVSS scores (Clause 6.1) | E27: Percentage | F27: Monthly | G27: =IF(COUNTIF([ISMS-IMP-A.5.7.3.xlsx]Risk_Assessment_Updates!F:F,"Vulnerability")=0,100,COUNTIFS([ISMS-IMP-A.5.7.3.xlsx]Risk_Assessment_Updates!F:F,"Vulnerability",[ISMS-IMP-A.5.7.3.xlsx]Risk_Assessment_Updates!H:H,"<>")/COUNTIF([ISMS-IMP-A.5.7.3.xlsx]Risk_Assessment_Updates!F:F,"Vulnerability")*100) | H27: 100% | I27: 95% | J27: 90% | M27: =IF(OR(K27="",H27=""),"N/A",(K27/H27-1)*100) | N27: =IF(K27="","N/A",IF(K27>=H27,"On_Track",IF(K27>=I27,"Caution","At_Risk"))) | O27: =IF(OR(K27="",L27=""),"N/A",IF(K27>L27,"Improving",IF(K27<L27,"Declining","Stable")))
A28: KPI-INC-001 | B28: Incident_Response | C28: Incidents with CVSS Context | D28: % of vulnerability incidents with CVSS data | E28: Percentage | F28: Monthly | G28: =IF(COUNTIF([ISMS-IMP-A.5.7.3.xlsx]Incident_TI_Integration!D:D,"Exploitation")=0,100,COUNTIFS([ISMS-IMP-A.5.7.3.xlsx]Incident_TI_Integration!D:D,"Exploitation",[ISMS-IMP-A.5.7.3.xlsx]Incident_TI_Integration!H:H,"<>")/COUNTIF([ISMS-IMP-A.5.7.3.xlsx]Incident_TI_Integration!D:D,"Exploitation")*100) | H28: 100% | I28: 90% | J28: 80% | M28: =IF(OR(K28="",H28=""),"N/A",(K28/H28-1)*100) | N28: =IF(K28="","N/A",IF(K28>=H28,"On_Track",IF(K28>=I28,"Caution","At_Risk"))) | O28: =IF(OR(K28="",L28=""),"N/A",IF(K28>L28,"Improving",IF(K28<L28,"Declining","Stable")))
A29: KPI-TI-025 | M29: =IF(OR(K29="",H29=""),"N/A",(K29/H29-1)*100) | N29: =IF(K29="","N/A",IF(K29>=H29,"On_Track",IF(K29>=I29,"Caution","At_Risk"))) | O29: =IF(OR(K29="",L29=""),"N/A",IF(K29>L29,"Improving",IF(K29<L29,"Declining","Stable")))
A30: KPI-TI-026 | M30: =IF(OR(K30="",H30=""),"N/A",(K30/H30-1)*100) | N30: =IF(K30="","N/A",IF(K30>=H30,"On_Track",IF(K30>=I30,"Caution","At_Risk"))) | O30: =IF(OR(K30="",L30=""),"N/A",IF(K30>L30,"Improving",IF(K30<L30,"Declining","Stable")))
A31: KPI-TI-027 | M31: =IF(OR(K31="",H31=""),"N/A",(K31/H31-1)*100) | N31: =IF(K31="","N/A",IF(K31>=H31,"On_Track",IF(K31>=I31,"Caution","At_Risk"))) | O31: =IF(OR(K31="",L31=""),"N/A",IF(K31>L31,"Improving",IF(K31<L31,"Declining","Stable")))
A32: KPI PERFORMANCE SUMMARY | M32: =IF(OR(K32="",H32=""),"N/A",(K32/H32-1)*100) | N32: =IF(K32="","N/A",IF(K32>=H32,"On_Track",IF(K32>=I32,"Caution","At_Risk"))) | O32: =IF(OR(K32="",L32=""),"N/A",IF(K32>L32,"Improving",IF(K32<L32,"Declining","Stable")))
A33: Total KPIs Tracked: | B33: =COUNTA(A5:A30) | M33: =IF(OR(K33="",H33=""),"N/A",(K33/H33-1)*100) | N33: =IF(K33="","N/A",IF(K33>=H33,"On_Track",IF(K33>=I33,"Caution","At_Risk"))) | O33: =IF(OR(K33="",L33=""),"N/A",IF(K33>L33,"Improving",IF(K33<L33,"Declining","Stable")))
A34: On Track: | B34: =COUNTIF(N5:N30,"On_Track") | M34: =IF(OR(K34="",H34=""),"N/A",(K34/H34-1)*100) | N34: =IF(K34="","N/A",IF(K34>=H34,"On_Track",IF(K34>=I34,"Caution","At_Risk"))) | O34: =IF(OR(K34="",L34=""),"N/A",IF(K34>L34,"Improving",IF(K34<L34,"Declining","Stable")))
A35: Caution: | B35: =COUNTIF(N5:N30,"Caution") | M35: =IF(OR(K35="",H35=""),"N/A",(K35/H35-1)*100) | N35: =IF(K35="","N/A",IF(K35>=H35,"On_Track",IF(K35>=I35,"Caution","At_Risk"))) | O35: =IF(OR(K35="",L35=""),"N/A",IF(K35>L35,"Improving",IF(K35<L35,"Declining","Stable")))
A36: At Risk: | B36: =COUNTIF(N5:N30,"At_Risk") | M36: =IF(OR(K36="",H36=""),"N/A",(K36/H36-1)*100) | N36: =IF(K36="","N/A",IF(K36>=H36,"On_Track",IF(K36>=I36,"Caution","At_Risk"))) | O36: =IF(OR(K36="",L36=""),"N/A",IF(K36>L36,"Improving",IF(K36<L36,"Declining","Stable")))
A37: Improving Trends: | B37: =COUNTIF(O5:O30,"Improving")
A38: Declining Trends: | B38: =COUNTIF(O5:O30,"Declining")

Sheet Source_Portfolio
A1: Source Portfolio Performance (from ISMS-IMP-A.5.7.1)
A2: Read-only aggregation from 5.7.1 Sources workbook. Update source workbook to refresh data here.
A3: ⚠️ External Reference: [ISMS-IMP-A.5.7.1.xlsx]
A5: SOURCE PORTFOLIO SUMMARY
A6: Total Active Sources: | C6: =COUNTA('[ISMS-IMP-A.5.7.1.xlsx]Source_Inventory'!A:A)-4
A7: Commercial Sources: | C7: =COUNTIF('[ISMS-IMP-A.5.7.1.xlsx]Source_Inventory'!C:C,"Commercial")
A8: OSINT Sources: | C8: =COUNTIF('[ISMS-IMP-A.5.7.1.xlsx]Source_Inventory'!C:C,"OSINT")
A9: Government Sources: | C9: =COUNTIF('[ISMS-IMP-A.5.7.1.xlsx]Source_Inventory'!C:C,"Government")
A10: Average Quality Score: | C10: =AVERAGE('[ISMS-IMP-A.5.7.1.xlsx]Source_Evaluation'!H:H)
A11: Sources Rated Excellent: | C11: =COUNTIF('[ISMS-IMP-A.5.7.1.xlsx]Source_Evaluation'!L:L,"Excellent")
A12: Coverage Gaps Identified: | C12: =COUNTIF('[ISMS-IMP-A.5.7.1.xlsx]Coverage_Matrix'!Status,"Gap")
A13: Annual Portfolio Cost: | C13: =SUM('[ISMS-IMP-A.5.7.1.xlsx]Cost_Analysis'!E:E)
A14: Compliance Issues: | C14: =COUNTIF('[ISMS-IMP-A.5.7.1.xlsx]Compliance_Check'!I:I,"Non_Compliant")
A17: TOP PERFORMING SOURCES (Quality Score)
A18: Source ID | B18: Source Name | C18: Type | D18: Quality Score | E18: Coverage Rating | F18: Cost Annual | G18: ROI Rating | H18: Recommendation | I18: Status | J18: Notes
A19: Note: Top sources require manual aggregation or advanced Excel formulas (SORT, FILTER - Excel 365)

Sheet Intelligence_Operations
A1: Intelligence Operations Metrics (from ISMS-IMP-A.5.7.2)
A2: Read-only aggregation from 5.7.2 Collection & Analysis workbook. Includes VTL metrics.
A3: ⚠️ External Reference: [ISMS-IMP-A.5.7.2.xlsx]
A5: COLLECTION COVERAGE | G5: INTELLIGENCE PRODUCTION
A6: Total Requirements: | C6: =COUNTA('[ISMS-IMP-A.5.7.2.xlsx]Collection_Coverage'!A:A)-4 | G6: Total Products: | I6: =COUNTA('[ISMS-IMP-A.5.7.2.xlsx]Intelligence_Production'!A:A)-4
A7: Adequate Coverage: | C7: =COUNTIF('[ISMS-IMP-A.5.7.2.xlsx]Collection_Coverage'!L:L,"Adequate") | G7: Published This Month: | I7: =COUNTIF('[ISMS-IMP-A.5.7.2.xlsx]Intelligence_Production'!N:N,"Published")
A8: Minimal Coverage: | C8: =COUNTIF('[ISMS-IMP-A.5.7.2.xlsx]Collection_Coverage'!L:L,"Minimal") | G8: Avg Feedback Rating: | I8: =AVERAGE('[ISMS-IMP-A.5.7.2.xlsx]Intelligence_Production'!J:J)
A9: Coverage Gaps: | C9: =COUNTIF('[ISMS-IMP-A.5.7.2.xlsx]Collection_Coverage'!L:L,"Gap") | G9: Avg Time to Produce: | I9: =AVERAGE('[ISMS-IMP-A.5.7.2.xlsx]Intelligence_Production'!M:M)
A12: MITRE ATT&CK COVERAGE | G12: VULNERABILITY-THREAT LINKS (VTL) ⚠️
A13: Total Techniques Tracked: | C13: =COUNTA('[ISMS-IMP-A.5.7.2.xlsx]MITRE_Mapping'!A:A)-4 | G13: Total VT Links: | I13: =COUNTA('[ISMS-IMP-A.5.7.2.xlsx]Vulnerability_Linked_Threats'!A:A)-4
A14: Full Coverage: | C14: =COUNTIF('[ISMS-IMP-A.5.7.2.xlsx]MITRE_Mapping'!F:F,"Full") | G14: Active Exploitation: | I14: =COUNTIF('[ISMS-IMP-A.5.7.2.xlsx]Vulnerability_Linked_Threats'!E:E,"Active_Exploitation")
A15: Partial Coverage: | C15: =COUNTIF('[ISMS-IMP-A.5.7.2.xlsx]MITRE_Mapping'!F:F,"Partial") | G15: Critical Assets Affected: | I15: =COUNTIF('[ISMS-IMP-A.5.7.2.xlsx]Vulnerability_Linked_Threats'!Q:Q,"Yes")
A16: No Coverage: | C16: =COUNTIF('[ISMS-IMP-A.5.7.2.xlsx]MITRE_Mapping'!F:F,"None") | G16: Remediation - Open: | I16: =COUNTIF('[ISMS-IMP-A.5.7.2.xlsx]Vulnerability_Linked_Threats'!R:R,"Open")
G17: Remediation - Patched: | I17: =COUNTIF('[ISMS-IMP-A.5.7.2.xlsx]Vulnerability_Linked_Threats'!R:R,"Patched")
A19: ANALYST TEAM CAPABILITY
A20: Total Analysts: | D20: =COUNTA('[ISMS-IMP-A.5.7.2.xlsx]Analyst_Capabilities'!A:A)-4
A21: Avg Years TI Experience: | D21: =AVERAGE('[ISMS-IMP-A.5.7.2.xlsx]Analyst_Capabilities'!F:F)
A22: Training Completion Rate: | D22: =AVERAGE('[ISMS-IMP-A.5.7.2.xlsx]Analyst_Capabilities'!J:J)
A23: Certifications Held: | D23: =COUNTA('[ISMS-IMP-A.5.7.2.xlsx]Analyst_Capabilities'!Q:Q)-4

Sheet Integration_Status
A1: Integration Status (from ISMS-IMP-A.5.7.3)
A2: Read-only aggregation from 5.7.3 Integration & Distribution workbook. Tool integration and IOC deployment metrics.
A3: ⚠️ External Reference: [ISMS-IMP-A.5.7.3.xlsx]
A5: SECURITY TOOL INTEGRATION | F5: IOC DEPLOYMENT & EFFECTIVENESS
A6: Total Security Tools: | C6: =COUNTA('[ISMS-IMP-A.5.7.3.xlsx]Tool_Integration_Matrix'!A:A)-4 | F6: Total IOCs Deployed: | H6: =COUNTA('[ISMS-IMP-A.5.7.3.xlsx]IOC_Deployment'!A:A)-4
A7: Fully Integrated: | C7: =COUNTIF('[ISMS-IMP-A.5.7.3.xlsx]Tool_Integration_Matrix'!D:D,"Full") | F7: Active IOCs: | H7: =COUNTIF('[ISMS-IMP-A.5.7.3.xlsx]IOC_Deployment'!I:I,"Active")
A8: Partially Integrated: | C8: =COUNTIF('[ISMS-IMP-A.5.7.3.xlsx]Tool_Integration_Matrix'!D:D,"Partial") | F8: Expired IOCs: | H8: =COUNTIF('[ISMS-IMP-A.5.7.3.xlsx]IOC_Deployment'!I:I,"Expired")
A9: Planned Integration: | C9: =COUNTIF('[ISMS-IMP-A.5.7.3.xlsx]Tool_Integration_Matrix'!D:D,"Planned") | F9: IOCs with Hits: | H9: =COUNTIF('[ISMS-IMP-A.5.7.3.xlsx]IOC_Deployment'!J:J,">0")
A10: Not Integrated: | C10: =COUNTIF('[ISMS-IMP-A.5.7.3.xlsx]Tool_Integration_Matrix'!D:D,"None") | F10: Hit Rate %: | H10: =COUNTIF('[ISMS-IMP-A.5.7.3.xlsx]IOC_Deployment'!J:J,">0")/COUNTA('[ISMS-IMP-A.5.7.3.xlsx]IOC_Deployment'!A:A)-4
A11: Integration Coverage %: | C11: =COUNTIF('[ISMS-IMP-A.5.7.3.xlsx]Tool_Integration_Matrix'!D:D,"Full")/COUNTA('[ISMS-IMP-A.5.7.3.xlsx]Tool_Integration_Matrix'!A:A)-4 | F11: Avg False Positives: | H11: =AVERAGE('[ISMS-IMP-A.5.7.3.xlsx]IOC_Deployment'!K:K)
A14: DISSEMINATION CHANNELS
A15: Total Channels Configured: | D15: =COUNTA('[ISMS-IMP-A.5.7.3.xlsx]Dissemination_Channels'!A:A)-4
A16: Active Channels: | D16: =COUNTIF('[ISMS-IMP-A.5.7.3.xlsx]Dissemination_Channels'!G:G,"Active")
A17: Distribution Events (Month): | D17: =COUNTA('[ISMS-IMP-A.5.7.3.xlsx]Distribution_Tracking'!A:A)-4
A18: Avg Distribution Time (hrs): | D18: =AVERAGE('[ISMS-IMP-A.5.7.3.xlsx]Distribution_Tracking'!TimeCol)
A21: INTEGRATION HEALTH INDICATORS
A22: Tools Requiring Attention: | D22: =COUNTIF('[ISMS-IMP-A.5.7.3.xlsx]Tool_Integration_Matrix'!J:J,"High")
A23: Integration Issues Open: | D23: =COUNTIF('[ISMS-IMP-A.5.7.3.xlsx]Tool_Integration_Matrix'!Issues,">0")
A24: IOCs Pending Deployment: | D24: =COUNTIF('[ISMS-IMP-A.5.7.3.xlsx]IOC_Deployment'!I:I,"Pending")
A25: Average Integration Maturity: | D25: Manual Calculation Required

Sheet Stakeholder_Engagement
A1: Stakeholder Engagement Metrics (from ISMS-IMP-A.5.7.3)
A2: Read-only aggregation from 5.7.3 Integration & Distribution workbook. Stakeholder feedback and engagement tracking.
A3: ⚠️ External Reference: [ISMS-IMP-A.5.7.3.xlsx]
A5: STAKEHOLDER REGISTRY
A6: Total Registered Stakeholders: | C6: =COUNTA('[ISMS-IMP-A.5.7.3.xlsx]Stakeholder_Registry'!A:A)-4
A7: Executive Level: | C7: =COUNTIF('[ISMS-IMP-A.5.7.3.xlsx]Stakeholder_Registry'!D:D,"Executive")
A8: Management Level: | C8: =COUNTIF('[ISMS-IMP-A.5.7.3.xlsx]Stakeholder_Registry'!D:D,"Management")
A9: Technical Level: | C9: =COUNTIF('[ISMS-IMP-A.5.7.3.xlsx]Stakeholder_Registry'!D:D,"Technical")
A10: Active Stakeholders: | C10: =COUNTIF('[ISMS-IMP-A.5.7.3.xlsx]Stakeholder_Registry'!Status,"Active")
A13: FEEDBACK & SATISFACTION
A14: Total Feedback Entries: | D14: =COUNTA('[ISMS-IMP-A.5.7.3.xlsx]Feedback_Collection'!A:A)-4
A15: Avg Relevance Rating (1-5): | D15: =AVERAGE('[ISMS-IMP-A.5.7.3.xlsx]Feedback_Collection'!D:D)
A16: Avg Timeliness Rating (1-5): | D16: =AVERAGE('[ISMS-IMP-A.5.7.3.xlsx]Feedback_Collection'!E:E)
A17: Avg Actionability Rating (1-5): | D17: =AVERAGE('[ISMS-IMP-A.5.7.3.xlsx]Feedback_Collection'!F:F)
A18: Overall Satisfaction (Avg): | D18: =AVERAGE('[ISMS-IMP-A.5.7.3.xlsx]Feedback_Collection'!D:F)
A19: Feedback Response Rate %: | D19: =COUNTA('[ISMS-IMP-A.5.7.3.xlsx]Feedback_Collection'!A:A)/COUNTA('[ISMS-IMP-A.5.7.3.xlsx]Distribution_Tracking'!A:A)
A22: ENGAGEMENT INDICATORS
A23: Intelligence Consumption Rate: | D23: =AVERAGE('[ISMS-IMP-A.5.7.2.xlsx]Intelligence_Production'!K:K)
A24: Stakeholder Reach This Month: | D24: =COUNTA('[ISMS-IMP-A.5.7.3.xlsx]Distribution_Tracking'!UniqueStakeholders)
A25: Distribution Events This Month: | D25: =COUNTA('[ISMS-IMP-A.5.7.3.xlsx]Distribution_Tracking'!A:A)-4
A26: Avg Time to Stakeholder Action: | D26: =AVERAGE('[ISMS-IMP-A.5.7.3.xlsx]Distribution_Tracking'!ActionTime)

Sheet Trend_Analysis
A1: Trend Analysis & Forecasting
A2: Track KPI trends over time. Manually update monthly data for trend analysis. Historical data enables forecasting.
A4: MONTHLY TREND DATA (Last 12 Months)
A5: Month | B5: Intel Products | C5: Avg Feedback Rating | D5: IOCs Deployed | E5: IOC Hit Rate % | F5: VT Links Created | G5: Active Sources | H5: Program Health Score
A6: 2025-02
A7: 2025-03
A8: 2025-04
A9: 2025-05
A10: 2025-06
A11: 2025-07
A12: 2025-08
A13: 2025-09
A14: 2025-10
A15: 2025-11
A16: 2025-12
A17: 2026-01
A19: TREND SUMMARY
A20: Avg Intel Products (12mo): | C20: =AVERAGE(B6:B17)
A21: Trend - Intel Products: | C21: =IF(B17>B6,"Increasing",IF(B17<B6,"Decreasing","Stable"))
A22: Avg Feedback Rating (12mo): | C22: =AVERAGE(C6:C17)
A23: Trend - Feedback: | C23: =IF(C17>C6,"Improving",IF(C17<C6,"Declining","Stable"))
A24: Avg IOC Hit Rate (12mo): | C24: =AVERAGE(E6:E17)
A25: Avg Program Health (12mo): | C25: =AVERAGE(H6:H17)
A28: 📈 FORECASTING & TREND CHARTS
A29: Trend charts should be created manually using the data above: - Line chart: Intel Products over time (B6:B17) - Line chart: Feedback Rating trend (C6:C17) - Line chart: Program Health Score (H6:H17) Use Excel's FORECAST.LINEAR function or trendlines for predictions.

Sheet Risk_Indicators
A1: Risk Indicators & Early Warnings
A2: Monitor risk indicators for TI program health. Set thresholds to trigger early warnings.
A4: Risk ID | B4: Risk Category | C4: Risk Indicator | D4: Current Value | E4: Warning Threshold | F4: Critical Threshold | G4: Risk Status | H4: Mitigation Action | I4: Owner
A5: RISK-001 | B5: Coverage | C5: Source Coverage Gaps | D5: =COUNTIF('[ISMS-IMP-A.5.7.1.xlsx]Coverage_Matrix'!Status,"Gap") | E5: 5 | F5: 10 | G5: =IF(D5="","N/A",IF(D5>F5,"Critical",IF(D5>E5,"Warning","Normal")))
A6: RISK-002 | B6: Production | C6: Intel Products Below Target | D6: =Program_KPIs!K5 | E6: 16 | F6: 12 | G6: =IF(D6="","N/A",IF(D6>F6,"Critical",IF(D6>E6,"Warning","Normal")))
A7: RISK-003 | B7: Quality | C7: Stakeholder Satisfaction Declining | D7: =Program_KPIs!K7 | E7: 3.5 | F7: 3.0 | G7: =IF(D7="","N/A",IF(D7>F7,"Critical",IF(D7>E7,"Warning","Normal")))
A8: RISK-004 | B8: Integration | C8: IOC Hit Rate Below Target | D8: =Program_KPIs!K14 | E8: 10% | F8: 5% | G8: =IF(D8="","N/A",IF(D8>F8,"Critical",IF(D8>E8,"Warning","Normal")))
A9: RISK-005 | B9: Integration | C9: IOC False Positive Rate High | D9: =Program_KPIs!K15 | E9: 10% | F9: 15% | G9: =IF(D9="","N/A",IF(D9>F9,"Critical",IF(D9>E9,"Warning","Normal")))
A10: RISK-006 | B10: Vulnerability | C10: Active Exploits Unpatched | D10: =COUNTIF('[ISMS-IMP-A.5.7.2.xlsx]Vulnerability_Linked_Threats'!R:R,"Open") | E10: 3 | F10: 5 | G10: =IF(D10="","N/A",IF(D10>F10,"Critical",IF(D10>E10,"Warning","Normal")))
A11: RISK-007 | B11: Team | C11: Analyst Training Incomplete | D11: =Program_KPIs!K10 | E11: 75% | F11: 60% | G11: =IF(D11="","N/A",IF(D11>F11,"Critical",IF(D11>E11,"Warning","Normal")))
A12: RISK-008 | B12: Coverage | C12: MITRE Coverage Gaps | D12: =COUNTIF('[ISMS-IMP-A.5.7.2.xlsx]MITRE_Mapping'!F:F,"None") | E12: 20 | F12: 30 | G12: =IF(D12="","N/A",IF(D12>F12,"Critical",IF(D12>E12,"Warning","Normal")))
A13: RISK-009 | B13: Compliance | C13: Evidence Items Outdated | D13: =COUNTIF(Compliance_Evidence!F:F,"Outdated") | E13: 3 | F13: 5 | G13: =IF(D13="","N/A",IF(D13>F13,"Critical",IF(D13>E13,"Warning","Normal")))
A14: RISK-010 | B14: Integration | C14: Tools Not Integrated | D14: =COUNTIF('[ISMS-IMP-A.5.7.3.xlsx]Tool_Integration_Matrix'!D:D,"None") | E14: 5 | F14: 8 | G14: =IF(D14="","N/A",IF(D14>F14,"Critical",IF(D14>E14,"Warning","Normal")))
A15: RISK-011 | G15: =IF(D15="","N/A",IF(D15>F15,"Critical",IF(D15>E15,"Warning","Normal")))
A16: RISK-012 | G16: =IF(D16="","N/A",IF(D16>F16,"Critical",IF(D16>E16,"Warning","Normal")))
A17: RISK-013 | G17: =IF(D17="","N/A",IF(D17>F17,"Critical",IF(D17>E17,"Warning","Normal")))
A18: RISK-014 | G18: =IF(D18="","N/A",IF(D18>F18,"Critical",IF(D18>E18,"Warning","Normal")))
A19: RISK-015 | G19: =IF(D19="","N/A",IF(D19>F19,"Critical",IF(D19>E19,"Warning","Normal")))
A20: RISK-016 | G20: =IF(D20="","N/A",IF(D20>F20,"Critical",IF(D20>E20,"Warning","Normal")))
A22: RISK SUMMARY
A23: Total Risks Monitored: | B23: =COUNTA(A5:A20)
A24: Critical Status: | B24: =COUNTIF(G5:G20,"Critical")
A25: Warning Status: | B25: =COUNTIF(G5:G20,"Warning")
A26: Normal Status: | B26: =COUNTIF(G5:G20,"Normal")
A30: CVSS-BASED RISK QUANTIFICATION (ISO 27001 Clause 6.1)
A31: Quarter | B31: Total Risk Updates | C31: Vulnerability-Related | D31: Risks with CVSS | E31: CVSS Quantification Rate | F31: Avg CVSS (Risks) | G31: Status
A32: =TEXT(TODAY(),"YYYY-\QQ") | B32: =COUNTA([ISMS-IMP-A.5.7.3.xlsx]Risk_Assessment_Updates!A:A)-3 | C32: =COUNTIF([ISMS-IMP-A.5.7.3.xlsx]Risk_Assessment_Updates!F:F,"Vulnerability") | D32: =COUNTIFS([ISMS-IMP-A.5.7.3.xlsx]Risk_Assessment_Updates!F:F,"Vulnerability",[ISMS-IMP-A.5.7.3.xlsx]Risk_Assessment_Updates!H:H,"<>") | E32: =IF(C32=0,"N/A",D32/C32) | F32: =AVERAGEIFS([ISMS-IMP-A.5.7.3.xlsx]Risk_Assessment_Updates!H:H,[ISMS-IMP-A.5.7.3.xlsx]Risk_Assessment_Updates!H:H,"<>") | G32: =IF(E32=1,"✅ Compliant",IF(E32>=0.9,"⚠️ Needs Attention","❌ Non-Compliant"))
A33: [Enter Quarter] | E33: =IF(C33=0,"N/A",D33/C33) | G33: =IF(E33=1,"✅ Compliant",IF(E33>=0.9,"⚠️ Needs Attention","❌ Non-Compliant"))
A34: [Enter Quarter] | E34: =IF(C34=0,"N/A",D34/C34) | G34: =IF(E34=1,"✅ Compliant",IF(E34>=0.9,"⚠️ Needs Attention","❌ Non-Compliant"))
A35: [Enter Quarter] | E35: =IF(C35=0,"N/A",D35/C35) | G35: =IF(E35=1,"✅ Compliant",IF(E35>=0.9,"⚠️ Needs Attention","❌ Non-Compliant"))
A36: [Enter Quarter] | E36: =IF(C36=0,"N/A",D36/C36) | G36: =IF(E36=1,"✅ Compliant",IF(E36>=0.9,"⚠️ Needs Attention","❌ Non-Compliant"))
A37: [Enter Quarter] | E37: =IF(C37=0,"N/A",D37/C37) | G37: =IF(E37=1,"✅ Compliant",IF(E37>=0.9,"⚠️ Needs Attention","❌ Non-Compliant"))
A38: 🎯 TARGET: 100% of vulnerability-related risks must have CVSS quantification for Clause 6.1 compliance

Sheet Compliance_Evidence
A1: Compliance Evidence - ISO 27001:2022 Control 5.7
A2: Audit evidence inventory for ISO 27001:2022 Control 5.7 (Threat Intelligence). Track evidence status and currency.
A4: Evidence ID | B4: Control Requirement | C4: Evidence Type | D4: Location | E4: Last Updated | F4: Status | G4: Notes
A5: EV-5.7-001 | B5: Source inventory maintained | C5: Excel Workbook | D5: ISMS-IMP-A.5.7.1 Sheet 2
A6: EV-5.7-002 | B6: Source quality assessed | C6: Excel Workbook | D6: ISMS-IMP-A.5.7.1 Sheet 3
A7: EV-5.7-003 | B7: Coverage gaps identified | C7: Excel Workbook | D7: ISMS-IMP-A.5.7.1 Sheet 4
A8: EV-5.7-004 | B8: Cost-benefit analysis performed | C8: Excel Workbook | D8: ISMS-IMP-A.5.7.1 Sheet 5
A9: EV-5.7-005 | B9: Compliance verification documented | C9: Excel Workbook | D9: ISMS-IMP-A.5.7.1 Sheet 6
A10: EV-5.7-006 | B10: Intelligence requirements defined | C10: Excel Workbook | D10: ISMS-IMP-A.5.7.2 Sheet 2
A11: EV-5.7-007 | B11: Analysis frameworks documented | C11: Excel Workbook | D11: ISMS-IMP-A.5.7.2 Sheet 3
A12: EV-5.7-008 | B12: Analyst capabilities tracked | C12: Excel Workbook | D12: ISMS-IMP-A.5.7.2 Sheet 4
A13: EV-5.7-009 | B13: Intelligence production tracked | C13: Excel Workbook | D13: ISMS-IMP-A.5.7.2 Sheet 5
A14: EV-5.7-010 | B14: MITRE mapping maintained | C14: Excel Workbook | D14: ISMS-IMP-A.5.7.2 Sheet 6
A15: EV-5.7-011 | B15: Quality metrics established | C15: Excel Workbook | D15: ISMS-IMP-A.5.7.2 Sheet 7
A16: EV-5.7-012 | B16: Vulnerability linkage (VTL schema) | C16: Excel Workbook | D16: ISMS-IMP-A.5.7.2 Sheet 8 (CRITICAL)
... A24: EV-5.7-020 | B24: Risk indicators monitored | C24: Excel Workbook | D24: ISMS-IMP-A.5.7.4 Sheet 8
A26: COMPLIANCE SUMMARY
A27: Total Evidence Items: | B27: =COUNTA(A5:A24)
A28: Current (< 90 days): | B28: =COUNTIF(F5:F24,"Current")
A29: Outdated (> 90 days): | B29: =COUNTIF(F5:F24,"Outdated")
A30: Missing: | B30: =COUNTIF(F5:F24,"Missing")
A31: Compliance Rate %: | B31: =COUNTIF(F5:F24,"Current")/COUNTA(A5:A24)

Sheet Monthly_Report
A1: Threat Intelligence Program - Monthly Report
A2: Report Period: February 2026 | D2: Generated: 08.02.2026
A4: 1. EXECUTIVE SUMMARY
A5: Program Health Score: [Auto from Executive_Summary] Key Achievements: [User completes] Areas Requiring Attention: [From Risk_Indicators]
A8: 2. KEY PERFORMANCE METRICS
A9: Intelligence Products Published: | C9: =Program_KPIs!K5
A10: Stakeholder Satisfaction: | C10: =Program_KPIs!K7
A11: IOCs Deployed: | C11: =Program_KPIs!K13
A12: Active Exploits Addressed: | C12: =COUNTIF('[ISMS-IMP-A.5.7.2.xlsx]Vulnerability_Linked_Threats'!R:R,"Patched")
A14: 3. INTEGRATION & DISTRIBUTION
A15: Tools Integrated: [From Integration_Status] IOC Hit Rate: [From Integration_Status] Distribution Reach: [From Stakeholder_Engagement]
A18: 4. CRITICAL ACTION ITEMS
A19: [User completes based on Risk_Indicators and open action items] Critical Risks: [From Risk_Indicators Critical count] Open High Priority Actions: [From source workbooks] Recommendations: [User input]

Sheet Quarterly_Report
A1: Threat Intelligence Program - Quarterly Report
A2: Report Period: Q1 2026 | D2: Generated: 08.02.2026
A4: 1. QUARTERLY EXECUTIVE SUMMARY
A5: [User completes with quarterly analysis and strategic insights]
A8: 2. STRATEGIC THREAT LANDSCAPE
A9: [User completes with quarterly analysis and strategic insights]
A12: 3. PROGRAM MATURITY ASSESSMENT
A13: [User completes with quarterly analysis and strategic insights]
A16: 4. QUARTERLY KPI PERFORMANCE
A17: [User completes with quarterly analysis and strategic insights]
A20: 5. SOURCE PORTFOLIO ROI ANALYSIS
A21: [User completes with quarterly analysis and strategic insights]
A24: 6. CONTROL 8.8 INTEGRATION REVIEW
A25: [User completes with quarterly analysis and strategic insights]
... A44: Note: This report requires manual completion with strategic insights. Aggregate data from Trend_Analysis sheet for quarterly trends. Reference Process_Maturity assessment from 5.7.2 Sheet 9.

Sheet Metadata
A1: Dashboard Metadata
A3: Document ID: | B3: ISMS-IMP-A.5.7.4
A4: Document Title: | B4: Threat Intelligence Effectiveness Dashboard
A5: ISO 27001:2022 Control: | B5: A.5.7 (Threat Intelligence)
A6: Version: | B6: 1.0
A7: Generated Date: | B7: 2026-02-08 12:25:43
A8: Generator Script: | B8: generate_a57_4_dashboard.py
A9: Python Version: | B9: 3.x
A10: Required Library: | B10: openpyxl
A12: Sheet Count: | B12: 12
A13: Sheet 1: | B13: Executive_Summary (C-level dashboard)
A14: Sheet 2: | B14: Program_KPIs (20 standard KPIs with external refs)
A15: Sheet 3: | B15: Source_Portfolio (aggregated from 5.7.1)
... A30: Setup Instructions: | B30: 1. Place all 5.7.x workbooks in same directory
B31: 2. Open this dashboard
B32: 3. Data → Edit Links → Update paths
B33: 4. Click 'Update' when prompted to refresh external links
B34: 5. Set target values in Program_KPIs sheet
B35: 6. Configure risk thresholds in Risk_Indicators
A37: Review Cycle: | B37: Monthly refresh, Quarterly deep review
A38: Policy Reference: | B38: ISMS-POL-A.5.7 (All Sections)
A39: Related Workbooks: | B39: ISMS-IMP-A.5.7.1, ISMS-IMP-A.5.7.2, ISMS-IMP-A.5.7.3
A41: Notes: | B41: External references enable auto-aggregation from source workbooks
B42: Charts and visualizations require manual creation or BI tools
B43: As Feynman said: 'The first principle is that you must not fool yourself'
B44: This dashboard synthesizes evidence, not theater.
